<vmap:VMAP xmlns:vmap="http://www.iab.net/videosuite/vmap" version="1.0">
    <vmap:AdBreak timeOffset="start" breakType="linear" breakId="preroll">
    <vmap:AdSource id="preroll-ad-1" allowMultipleAds="false" followRedirects="true">
      <vmap:AdTagURI templateType="vast3">
        <![CDATA[https://pubads.g.doubleclick.net/gampad/ads?slotname=/21723553151/Test/Test_MXPlayer_Video1&amp;sz=400x300%7C640x480&amp;ciu_szs=1440x240&amp;cust_params=sg%3D30b,3g2,3g4,jaz,jbc,2v6,2vh,2vk,2x6,2vt,2vy,5lz,2wl,2wp,5o2,5o8,3iv,jwp,5oa,lkh,5oc,5oe,5of,5og,5op,gau,nr2,iwk,jyq,i5v,o1n,nqv,nqx,o1v,nqy,o1z,ixn,o2a,8gr,ixv,8gv,8gw,3nn,3nq,o3b,7gl,7gm,8it,8k8,8ix,8iy,8l4,8js,mss,jo3,jo8,8ke,8kf,jo9,jnm,jog,3si,cu3,k1m,352,k1w,k2h,8r7,i10,jtl,l85,hr2,80q,80s,80t,l7m,hqv,atp,5mt,oa3,k88,k87,ll7,5od,k8b,k8a,k8d,5q5,k8e,k8j,k8l,k8m,k8r,k8q,i63,o24,o25,o28,o29,k9i,k9h,k9k,iwl,k9l,k9o,k9n,lmf,lme,k9t,k9w,k9v,o1s,o1u,o1t,o1w,o1y,o1x,ocj,o40,3nf,7h6,o50,o57,o3t,hhg,ofb,ka1,ka0,ogx,69m,33k,33p,3g1,3g5,34o,34s,poa,3h8,poc,pog,3gc,cx5,3hb,cwb,3hi,5n4,3j3,3hq,3hw,cy9,cwv,cxa,cz8,3iw,oa4,6a1,cye,3l0,3l2,czd,3ku,6c0,i66,i5w,3me,ai8,3o1,3mu,nap,7g0,7g5,naz,j8v,3ni,h5x,h80,h82,hyg,nf1,oh1,nf2,msm,msl,mso,ikm,g5x,ogq,5eo,ogy,7k5,7k6,7k8,nfb,nff,jny,6hp,6hs,nge,ngi,k18%26vrsn%3DGP_1.27.1.0.charles.0.debug&amp;url=https://www.mxplayer.in/detail/episode/d39914eee9c3d50e21b81e01e8307eaf&amp;unviewed_position_start=1&amp;output=xml_vast3&amp;impl=s&amp;env=vp&amp;gdfp_req=1&amp;ad_rule=0&amp;video_url_to_fetch=https://www.mxplayer.in/detail/episode/d39914eee9c3d50e21b81e01e8307eaf&amp;vad_type=linear&amp;vpos=preroll&amp;pod=1&amp;ppos=1&amp;lip=true&amp;min_ad_duration=0&amp;max_ad_duration=250000&amp;vrid=1118784&amp;rdid=2d43e6e5-f1ec-47a8-81b1-10ca1ad1abe1&amp;is_amp=0&amp;dt=1599121523307&amp;idt=416&amp;dlt=1599121522102&amp;correlator=1950702064322958&amp;scor=1681105612848119&amp;sdk_apis=7,8&amp;omid_p=Google1/android.3.11.3&amp;osd=2&amp;vis=1&amp;npa=false&amp;hl=en&amp;frm=0&amp;video_doc_id=d39914eee9c3d50e21b81e01e8307eaf&amp;cmsid=2481704&amp;sdkv=h.3.237.0/n.android.3.11.3/com.mxtech.videoplayer.ad&amp;sdki=405&amp;mpt=google/exo.ext.ima&amp;mpv=2.11.3&amp;sdr=1&amp;eid=44725356&amp;an=com.mxtech.videoplayer.ad&amp;js=ima-android.3.11.3&amp;msid=com.mxtech.videoplayer.ad&amp;u_so=l&amp;is_lat=false&amp;idtype=adid&amp;mv=82161310.com.android.vending&amp;kfa=0&amp;tfcd=0]]>
      </vmap:AdTagURI>
    </vmap:AdSource>
  </vmap:AdBreak>
  <vmap:AdBreak timeOffset="00:02:00.000" breakType="linear" breakId="midroll-1">
    <vmap:AdSource id="midroll-1-ads" allowMultipleAds="true" followRedirects="true">
      <vmap:AdTagURI templateType="vast3">
        <![CDATA[https://pubads.g.doubleclick.net/gampad/ads?slotname=/21723553151/Test/Test_MXPlayer_Video1&amp;sz=400x300%7C640x480&amp;ciu_szs=1440x240&amp;cust_params=sg%3D30b,3g2,3g4,jaz,jbc,2v6,2vh,2vk,2x6,2vt,2vy,5lz,2wl,2wp,5o2,5o8,3iv,jwp,5oa,lkh,5oc,5oe,5of,5og,5op,gau,nr2,iwk,jyq,i5v,o1n,nqv,nqx,o1v,nqy,o1z,ixn,o2a,8gr,ixv,8gv,8gw,3nn,3nq,o3b,7gl,7gm,8it,8k8,8ix,8iy,8l4,8js,mss,jo3,jo8,8ke,8kf,jo9,jnm,jog,3si,cu3,k1m,352,k1w,k2h,8r7,i10,jtl,l85,hr2,80q,80s,80t,l7m,hqv,atp,5mt,oa3,k88,k87,ll7,5od,k8b,k8a,k8d,5q5,k8e,k8j,k8l,k8m,k8r,k8q,i63,o24,o25,o28,o29,k9i,k9h,k9k,iwl,k9l,k9o,k9n,lmf,lme,k9t,k9w,k9v,o1s,o1u,o1t,o1w,o1y,o1x,ocj,o40,3nf,7h6,o50,o57,o3t,hhg,ofb,ka1,ka0,ogx,69m,33k,33p,3g1,3g5,34o,34s,poa,3h8,poc,pog,3gc,cx5,3hb,cwb,3hi,5n4,3j3,3hq,3hw,cy9,cwv,cxa,cz8,3iw,oa4,6a1,cye,3l0,3l2,czd,3ku,6c0,i66,i5w,3me,ai8,3o1,3mu,nap,7g0,7g5,naz,j8v,3ni,h5x,h80,h82,hyg,nf1,oh1,nf2,msm,msl,mso,ikm,g5x,ogq,5eo,ogy,7k5,7k6,7k8,nfb,nff,jny,6hp,6hs,nge,ngi,k18%26vrsn%3DGP_1.27.1.0.charles.0.debug&amp;url=https://www.mxplayer.in/detail/episode/d39914eee9c3d50e21b81e01e8307eaf&amp;unviewed_position_start=1&amp;output=xml_vast3&amp;impl=s&amp;env=vp&amp;gdfp_req=1&amp;ad_rule=0&amp;video_url_to_fetch=https://www.mxplayer.in/detail/episode/d39914eee9c3d50e21b81e01e8307eaf&amp;cue=120000&amp;vad_type=linear&amp;vpos=midroll&amp;pod=2&amp;mridx=1&amp;rmridx=25&amp;pmnd=0&amp;pmxd=60000&amp;pmad=2&amp;vrid=1118784&amp;rdid=2d43e6e5-f1ec-47a8-81b1-10ca1ad1abe1&amp;is_amp=0&amp;dt=1599121523307&amp;idt=416&amp;dlt=1599121522102&amp;correlator=1950702064322958&amp;scor=1681105612848119&amp;sdk_apis=7,8&amp;omid_p=Google1/android.3.11.3&amp;osd=2&amp;vis=1&amp;npa=false&amp;hl=en&amp;frm=0&amp;video_doc_id=d39914eee9c3d50e21b81e01e8307eaf&amp;cmsid=2481704&amp;sdkv=h.3.237.0/n.android.3.11.3/com.mxtech.videoplayer.ad&amp;sdki=405&amp;mpt=google/exo.ext.ima&amp;mpv=2.11.3&amp;sdr=1&amp;eid=44725356&amp;an=com.mxtech.videoplayer.ad&amp;js=ima-android.3.11.3&amp;msid=com.mxtech.videoplayer.ad&amp;u_so=l&amp;is_lat=false&amp;idtype=adid&amp;mv=82161310.com.android.vending&amp;kfa=0&amp;tfcd=0]]>
      </vmap:AdTagURI>
    </vmap:AdSource>
  </vmap:AdBreak>
  <vmap:AdBreak timeOffset="00:04:00.000" breakType="linear" breakId="midroll-2">
    <vmap:AdSource id="midroll-2-ads" allowMultipleAds="true" followRedirects="true">
      <vmap:AdTagURI templateType="vast3">
        <![CDATA[https://pubads.g.doubleclick.net/gampad/ads?slotname=/21723553151/Test/Test_MXPlayer_Video1&amp;sz=400x300%7C640x480&amp;ciu_szs=1440x240&amp;cust_params=sg%3D30b,3g2,3g4,jaz,jbc,2v6,2vh,2vk,2x6,2vt,2vy,5lz,2wl,2wp,5o2,5o8,3iv,jwp,5oa,lkh,5oc,5oe,5of,5og,5op,gau,nr2,iwk,jyq,i5v,o1n,nqv,nqx,o1v,nqy,o1z,ixn,o2a,8gr,ixv,8gv,8gw,3nn,3nq,o3b,7gl,7gm,8it,8k8,8ix,8iy,8l4,8js,mss,jo3,jo8,8ke,8kf,jo9,jnm,jog,3si,cu3,k1m,352,k1w,k2h,8r7,i10,jtl,l85,hr2,80q,80s,80t,l7m,hqv,atp,5mt,oa3,k88,k87,ll7,5od,k8b,k8a,k8d,5q5,k8e,k8j,k8l,k8m,k8r,k8q,i63,o24,o25,o28,o29,k9i,k9h,k9k,iwl,k9l,k9o,k9n,lmf,lme,k9t,k9w,k9v,o1s,o1u,o1t,o1w,o1y,o1x,ocj,o40,3nf,7h6,o50,o57,o3t,hhg,ofb,ka1,ka0,ogx,69m,33k,33p,3g1,3g5,34o,34s,poa,3h8,poc,pog,3gc,cx5,3hb,cwb,3hi,5n4,3j3,3hq,3hw,cy9,cwv,cxa,cz8,3iw,oa4,6a1,cye,3l0,3l2,czd,3ku,6c0,i66,i5w,3me,ai8,3o1,3mu,nap,7g0,7g5,naz,j8v,3ni,h5x,h80,h82,hyg,nf1,oh1,nf2,msm,msl,mso,ikm,g5x,ogq,5eo,ogy,7k5,7k6,7k8,nfb,nff,jny,6hp,6hs,nge,ngi,k18%26vrsn%3DGP_1.27.1.0.charles.0.debug&amp;url=https://www.mxplayer.in/detail/episode/d39914eee9c3d50e21b81e01e8307eaf&amp;unviewed_position_start=1&amp;output=xml_vast3&amp;impl=s&amp;env=vp&amp;gdfp_req=1&amp;ad_rule=0&amp;video_url_to_fetch=https://www.mxplayer.in/detail/episode/d39914eee9c3d50e21b81e01e8307eaf&amp;cue=240000&amp;vad_type=linear&amp;vpos=midroll&amp;pod=3&amp;mridx=2&amp;rmridx=24&amp;pmnd=0&amp;pmxd=60000&amp;pmad=2&amp;vrid=1118784&amp;rdid=2d43e6e5-f1ec-47a8-81b1-10ca1ad1abe1&amp;is_amp=0&amp;dt=1599121523307&amp;idt=416&amp;dlt=1599121522102&amp;correlator=1950702064322958&amp;scor=1681105612848119&amp;sdk_apis=7,8&amp;omid_p=Google1/android.3.11.3&amp;osd=2&amp;vis=1&amp;npa=false&amp;hl=en&amp;frm=0&amp;video_doc_id=d39914eee9c3d50e21b81e01e8307eaf&amp;cmsid=2481704&amp;sdkv=h.3.237.0/n.android.3.11.3/com.mxtech.videoplayer.ad&amp;sdki=405&amp;mpt=google/exo.ext.ima&amp;mpv=2.11.3&amp;sdr=1&amp;eid=44725356&amp;an=com.mxtech.videoplayer.ad&amp;js=ima-android.3.11.3&amp;msid=com.mxtech.videoplayer.ad&amp;u_so=l&amp;is_lat=false&amp;idtype=adid&amp;mv=82161310.com.android.vending&amp;kfa=0&amp;tfcd=0]]>
      </vmap:AdTagURI>
    </vmap:AdSource>
  </vmap:AdBreak>
  <vmap:AdBreak timeOffset="00:06:00.000" breakType="linear" breakId="midroll-3">
    <vmap:AdSource id="midroll-3-ads" allowMultipleAds="true" followRedirects="true">
      <vmap:AdTagURI templateType="vast3">
        <![CDATA[https://pubads.g.doubleclick.net/gampad/ads?slotname=/21723553151/Test/Test_MXPlayer_Video1&amp;sz=400x300%7C640x480&amp;ciu_szs=1440x240&amp;cust_params=sg%3D30b,3g2,3g4,jaz,jbc,2v6,2vh,2vk,2x6,2vt,2vy,5lz,2wl,2wp,5o2,5o8,3iv,jwp,5oa,lkh,5oc,5oe,5of,5og,5op,gau,nr2,iwk,jyq,i5v,o1n,nqv,nqx,o1v,nqy,o1z,ixn,o2a,8gr,ixv,8gv,8gw,3nn,3nq,o3b,7gl,7gm,8it,8k8,8ix,8iy,8l4,8js,mss,jo3,jo8,8ke,8kf,jo9,jnm,jog,3si,cu3,k1m,352,k1w,k2h,8r7,i10,jtl,l85,hr2,80q,80s,80t,l7m,hqv,atp,5mt,oa3,k88,k87,ll7,5od,k8b,k8a,k8d,5q5,k8e,k8j,k8l,k8m,k8r,k8q,i63,o24,o25,o28,o29,k9i,k9h,k9k,iwl,k9l,k9o,k9n,lmf,lme,k9t,k9w,k9v,o1s,o1u,o1t,o1w,o1y,o1x,ocj,o40,3nf,7h6,o50,o57,o3t,hhg,ofb,ka1,ka0,ogx,69m,33k,33p,3g1,3g5,34o,34s,poa,3h8,poc,pog,3gc,cx5,3hb,cwb,3hi,5n4,3j3,3hq,3hw,cy9,cwv,cxa,cz8,3iw,oa4,6a1,cye,3l0,3l2,czd,3ku,6c0,i66,i5w,3me,ai8,3o1,3mu,nap,7g0,7g5,naz,j8v,3ni,h5x,h80,h82,hyg,nf1,oh1,nf2,msm,msl,mso,ikm,g5x,ogq,5eo,ogy,7k5,7k6,7k8,nfb,nff,jny,6hp,6hs,nge,ngi,k18%26vrsn%3DGP_1.27.1.0.charles.0.debug&amp;url=https://www.mxplayer.in/detail/episode/d39914eee9c3d50e21b81e01e8307eaf&amp;unviewed_position_start=1&amp;output=xml_vast3&amp;impl=s&amp;env=vp&amp;gdfp_req=1&amp;ad_rule=0&amp;video_url_to_fetch=https://www.mxplayer.in/detail/episode/d39914eee9c3d50e21b81e01e8307eaf&amp;cue=360000&amp;vad_type=linear&amp;vpos=midroll&amp;pod=4&amp;mridx=3&amp;rmridx=23&amp;pmnd=0&amp;pmxd=60000&amp;pmad=2&amp;vrid=1118784&amp;rdid=2d43e6e5-f1ec-47a8-81b1-10ca1ad1abe1&amp;is_amp=0&amp;dt=1599121523307&amp;idt=416&amp;dlt=1599121522102&amp;correlator=1950702064322958&amp;scor=1681105612848119&amp;sdk_apis=7,8&amp;omid_p=Google1/android.3.11.3&amp;osd=2&amp;vis=1&amp;npa=false&amp;hl=en&amp;frm=0&amp;video_doc_id=d39914eee9c3d50e21b81e01e8307eaf&amp;cmsid=2481704&amp;sdkv=h.3.237.0/n.android.3.11.3/com.mxtech.videoplayer.ad&amp;sdki=405&amp;mpt=google/exo.ext.ima&amp;mpv=2.11.3&amp;sdr=1&amp;eid=44725356&amp;an=com.mxtech.videoplayer.ad&amp;js=ima-android.3.11.3&amp;msid=com.mxtech.videoplayer.ad&amp;u_so=l&amp;is_lat=false&amp;idtype=adid&amp;mv=82161310.com.android.vending&amp;kfa=0&amp;tfcd=0]]>
      </vmap:AdTagURI>
    </vmap:AdSource>
  </vmap:AdBreak>
  <vmap:AdBreak timeOffset="00:08:00.000" breakType="linear" breakId="midroll-4">
    <vmap:AdSource id="midroll-4-ads" allowMultipleAds="true" followRedirects="true">
      <vmap:AdTagURI templateType="vast3">
        <![CDATA[https://pubads.g.doubleclick.net/gampad/ads?slotname=/21723553151/Test/Test_MXPlayer_Video1&amp;sz=400x300%7C640x480&amp;ciu_szs=1440x240&amp;cust_params=sg%3D30b,3g2,3g4,jaz,jbc,2v6,2vh,2vk,2x6,2vt,2vy,5lz,2wl,2wp,5o2,5o8,3iv,jwp,5oa,lkh,5oc,5oe,5of,5og,5op,gau,nr2,iwk,jyq,i5v,o1n,nqv,nqx,o1v,nqy,o1z,ixn,o2a,8gr,ixv,8gv,8gw,3nn,3nq,o3b,7gl,7gm,8it,8k8,8ix,8iy,8l4,8js,mss,jo3,jo8,8ke,8kf,jo9,jnm,jog,3si,cu3,k1m,352,k1w,k2h,8r7,i10,jtl,l85,hr2,80q,80s,80t,l7m,hqv,atp,5mt,oa3,k88,k87,ll7,5od,k8b,k8a,k8d,5q5,k8e,k8j,k8l,k8m,k8r,k8q,i63,o24,o25,o28,o29,k9i,k9h,k9k,iwl,k9l,k9o,k9n,lmf,lme,k9t,k9w,k9v,o1s,o1u,o1t,o1w,o1y,o1x,ocj,o40,3nf,7h6,o50,o57,o3t,hhg,ofb,ka1,ka0,ogx,69m,33k,33p,3g1,3g5,34o,34s,poa,3h8,poc,pog,3gc,cx5,3hb,cwb,3hi,5n4,3j3,3hq,3hw,cy9,cwv,cxa,cz8,3iw,oa4,6a1,cye,3l0,3l2,czd,3ku,6c0,i66,i5w,3me,ai8,3o1,3mu,nap,7g0,7g5,naz,j8v,3ni,h5x,h80,h82,hyg,nf1,oh1,nf2,msm,msl,mso,ikm,g5x,ogq,5eo,ogy,7k5,7k6,7k8,nfb,nff,jny,6hp,6hs,nge,ngi,k18%26vrsn%3DGP_1.27.1.0.charles.0.debug&amp;url=https://www.mxplayer.in/detail/episode/d39914eee9c3d50e21b81e01e8307eaf&amp;unviewed_position_start=1&amp;output=xml_vast3&amp;impl=s&amp;env=vp&amp;gdfp_req=1&amp;ad_rule=0&amp;video_url_to_fetch=https://www.mxplayer.in/detail/episode/d39914eee9c3d50e21b81e01e8307eaf&amp;cue=480000&amp;vad_type=linear&amp;vpos=midroll&amp;pod=5&amp;mridx=4&amp;rmridx=22&amp;pmnd=0&amp;pmxd=60000&amp;pmad=2&amp;vrid=1118784&amp;rdid=2d43e6e5-f1ec-47a8-81b1-10ca1ad1abe1&amp;is_amp=0&amp;dt=1599121523307&amp;idt=416&amp;dlt=1599121522102&amp;correlator=1950702064322958&amp;scor=1681105612848119&amp;sdk_apis=7,8&amp;omid_p=Google1/android.3.11.3&amp;osd=2&amp;vis=1&amp;npa=false&amp;hl=en&amp;frm=0&amp;video_doc_id=d39914eee9c3d50e21b81e01e8307eaf&amp;cmsid=2481704&amp;sdkv=h.3.237.0/n.android.3.11.3/com.mxtech.videoplayer.ad&amp;sdki=405&amp;mpt=google/exo.ext.ima&amp;mpv=2.11.3&amp;sdr=1&amp;eid=44725356&amp;an=com.mxtech.videoplayer.ad&amp;js=ima-android.3.11.3&amp;msid=com.mxtech.videoplayer.ad&amp;u_so=l&amp;is_lat=false&amp;idtype=adid&amp;mv=82161310.com.android.vending&amp;kfa=0&amp;tfcd=0]]>
      </vmap:AdTagURI>
    </vmap:AdSource>
  </vmap:AdBreak>
  <vmap:AdBreak timeOffset="00:10:00.000" breakType="linear" breakId="midroll-5">
    <vmap:AdSource id="midroll-5-ads" allowMultipleAds="true" followRedirects="true">
      <vmap:AdTagURI templateType="vast3">
        <![CDATA[https://pubads.g.doubleclick.net/gampad/ads?slotname=/21723553151/Test/Test_MXPlayer_Video1&amp;sz=400x300%7C640x480&amp;ciu_szs=1440x240&amp;cust_params=sg%3D30b,3g2,3g4,jaz,jbc,2v6,2vh,2vk,2x6,2vt,2vy,5lz,2wl,2wp,5o2,5o8,3iv,jwp,5oa,lkh,5oc,5oe,5of,5og,5op,gau,nr2,iwk,jyq,i5v,o1n,nqv,nqx,o1v,nqy,o1z,ixn,o2a,8gr,ixv,8gv,8gw,3nn,3nq,o3b,7gl,7gm,8it,8k8,8ix,8iy,8l4,8js,mss,jo3,jo8,8ke,8kf,jo9,jnm,jog,3si,cu3,k1m,352,k1w,k2h,8r7,i10,jtl,l85,hr2,80q,80s,80t,l7m,hqv,atp,5mt,oa3,k88,k87,ll7,5od,k8b,k8a,k8d,5q5,k8e,k8j,k8l,k8m,k8r,k8q,i63,o24,o25,o28,o29,k9i,k9h,k9k,iwl,k9l,k9o,k9n,lmf,lme,k9t,k9w,k9v,o1s,o1u,o1t,o1w,o1y,o1x,ocj,o40,3nf,7h6,o50,o57,o3t,hhg,ofb,ka1,ka0,ogx,69m,33k,33p,3g1,3g5,34o,34s,poa,3h8,poc,pog,3gc,cx5,3hb,cwb,3hi,5n4,3j3,3hq,3hw,cy9,cwv,cxa,cz8,3iw,oa4,6a1,cye,3l0,3l2,czd,3ku,6c0,i66,i5w,3me,ai8,3o1,3mu,nap,7g0,7g5,naz,j8v,3ni,h5x,h80,h82,hyg,nf1,oh1,nf2,msm,msl,mso,ikm,g5x,ogq,5eo,ogy,7k5,7k6,7k8,nfb,nff,jny,6hp,6hs,nge,ngi,k18%26vrsn%3DGP_1.27.1.0.charles.0.debug&amp;url=https://www.mxplayer.in/detail/episode/d39914eee9c3d50e21b81e01e8307eaf&amp;unviewed_position_start=1&amp;output=xml_vast3&amp;impl=s&amp;env=vp&amp;gdfp_req=1&amp;ad_rule=0&amp;video_url_to_fetch=https://www.mxplayer.in/detail/episode/d39914eee9c3d50e21b81e01e8307eaf&amp;cue=600000&amp;vad_type=linear&amp;vpos=midroll&amp;pod=6&amp;mridx=5&amp;rmridx=21&amp;pmnd=0&amp;pmxd=60000&amp;pmad=2&amp;vrid=1118784&amp;rdid=2d43e6e5-f1ec-47a8-81b1-10ca1ad1abe1&amp;is_amp=0&amp;dt=1599121523307&amp;idt=416&amp;dlt=1599121522102&amp;correlator=1950702064322958&amp;scor=1681105612848119&amp;sdk_apis=7,8&amp;omid_p=Google1/android.3.11.3&amp;osd=2&amp;vis=1&amp;npa=false&amp;hl=en&amp;frm=0&amp;video_doc_id=d39914eee9c3d50e21b81e01e8307eaf&amp;cmsid=2481704&amp;sdkv=h.3.237.0/n.android.3.11.3/com.mxtech.videoplayer.ad&amp;sdki=405&amp;mpt=google/exo.ext.ima&amp;mpv=2.11.3&amp;sdr=1&amp;eid=44725356&amp;an=com.mxtech.videoplayer.ad&amp;js=ima-android.3.11.3&amp;msid=com.mxtech.videoplayer.ad&amp;u_so=l&amp;is_lat=false&amp;idtype=adid&amp;mv=82161310.com.android.vending&amp;kfa=0&amp;tfcd=0]]>
      </vmap:AdTagURI>
    </vmap:AdSource>
  </vmap:AdBreak>
  <vmap:AdBreak timeOffset="00:12:00.000" breakType="linear" breakId="midroll-6">
    <vmap:AdSource id="midroll-6-ads" allowMultipleAds="true" followRedirects="true">
      <vmap:AdTagURI templateType="vast3">
        <![CDATA[https://pubads.g.doubleclick.net/gampad/ads?slotname=/21723553151/Test/Test_MXPlayer_Video1&amp;sz=400x300%7C640x480&amp;ciu_szs=1440x240&amp;cust_params=sg%3D30b,3g2,3g4,jaz,jbc,2v6,2vh,2vk,2x6,2vt,2vy,5lz,2wl,2wp,5o2,5o8,3iv,jwp,5oa,lkh,5oc,5oe,5of,5og,5op,gau,nr2,iwk,jyq,i5v,o1n,nqv,nqx,o1v,nqy,o1z,ixn,o2a,8gr,ixv,8gv,8gw,3nn,3nq,o3b,7gl,7gm,8it,8k8,8ix,8iy,8l4,8js,mss,jo3,jo8,8ke,8kf,jo9,jnm,jog,3si,cu3,k1m,352,k1w,k2h,8r7,i10,jtl,l85,hr2,80q,80s,80t,l7m,hqv,atp,5mt,oa3,k88,k87,ll7,5od,k8b,k8a,k8d,5q5,k8e,k8j,k8l,k8m,k8r,k8q,i63,o24,o25,o28,o29,k9i,k9h,k9k,iwl,k9l,k9o,k9n,lmf,lme,k9t,k9w,k9v,o1s,o1u,o1t,o1w,o1y,o1x,ocj,o40,3nf,7h6,o50,o57,o3t,hhg,ofb,ka1,ka0,ogx,69m,33k,33p,3g1,3g5,34o,34s,poa,3h8,poc,pog,3gc,cx5,3hb,cwb,3hi,5n4,3j3,3hq,3hw,cy9,cwv,cxa,cz8,3iw,oa4,6a1,cye,3l0,3l2,czd,3ku,6c0,i66,i5w,3me,ai8,3o1,3mu,nap,7g0,7g5,naz,j8v,3ni,h5x,h80,h82,hyg,nf1,oh1,nf2,msm,msl,mso,ikm,g5x,ogq,5eo,ogy,7k5,7k6,7k8,nfb,nff,jny,6hp,6hs,nge,ngi,k18%26vrsn%3DGP_1.27.1.0.charles.0.debug&amp;url=https://www.mxplayer.in/detail/episode/d39914eee9c3d50e21b81e01e8307eaf&amp;unviewed_position_start=1&amp;output=xml_vast3&amp;impl=s&amp;env=vp&amp;gdfp_req=1&amp;ad_rule=0&amp;video_url_to_fetch=https://www.mxplayer.in/detail/episode/d39914eee9c3d50e21b81e01e8307eaf&amp;cue=720000&amp;vad_type=linear&amp;vpos=midroll&amp;pod=7&amp;mridx=6&amp;rmridx=20&amp;pmnd=0&amp;pmxd=60000&amp;pmad=2&amp;vrid=1118784&amp;rdid=2d43e6e5-f1ec-47a8-81b1-10ca1ad1abe1&amp;is_amp=0&amp;dt=1599121523307&amp;idt=416&amp;dlt=1599121522102&amp;correlator=1950702064322958&amp;scor=1681105612848119&amp;sdk_apis=7,8&amp;omid_p=Google1/android.3.11.3&amp;osd=2&amp;vis=1&amp;npa=false&amp;hl=en&amp;frm=0&amp;video_doc_id=d39914eee9c3d50e21b81e01e8307eaf&amp;cmsid=2481704&amp;sdkv=h.3.237.0/n.android.3.11.3/com.mxtech.videoplayer.ad&amp;sdki=405&amp;mpt=google/exo.ext.ima&amp;mpv=2.11.3&amp;sdr=1&amp;eid=44725356&amp;an=com.mxtech.videoplayer.ad&amp;js=ima-android.3.11.3&amp;msid=com.mxtech.videoplayer.ad&amp;u_so=l&amp;is_lat=false&amp;idtype=adid&amp;mv=82161310.com.android.vending&amp;kfa=0&amp;tfcd=0]]>
      </vmap:AdTagURI>
    </vmap:AdSource>
  </vmap:AdBreak>
  <vmap:AdBreak timeOffset="00:14:00.000" breakType="linear" breakId="midroll-7">
    <vmap:AdSource id="midroll-7-ads" allowMultipleAds="true" followRedirects="true">
      <vmap:AdTagURI templateType="vast3">
        <![CDATA[https://pubads.g.doubleclick.net/gampad/ads?slotname=/21723553151/Test/Test_MXPlayer_Video1&amp;sz=400x300%7C640x480&amp;ciu_szs=1440x240&amp;cust_params=sg%3D30b,3g2,3g4,jaz,jbc,2v6,2vh,2vk,2x6,2vt,2vy,5lz,2wl,2wp,5o2,5o8,3iv,jwp,5oa,lkh,5oc,5oe,5of,5og,5op,gau,nr2,iwk,jyq,i5v,o1n,nqv,nqx,o1v,nqy,o1z,ixn,o2a,8gr,ixv,8gv,8gw,3nn,3nq,o3b,7gl,7gm,8it,8k8,8ix,8iy,8l4,8js,mss,jo3,jo8,8ke,8kf,jo9,jnm,jog,3si,cu3,k1m,352,k1w,k2h,8r7,i10,jtl,l85,hr2,80q,80s,80t,l7m,hqv,atp,5mt,oa3,k88,k87,ll7,5od,k8b,k8a,k8d,5q5,k8e,k8j,k8l,k8m,k8r,k8q,i63,o24,o25,o28,o29,k9i,k9h,k9k,iwl,k9l,k9o,k9n,lmf,lme,k9t,k9w,k9v,o1s,o1u,o1t,o1w,o1y,o1x,ocj,o40,3nf,7h6,o50,o57,o3t,hhg,ofb,ka1,ka0,ogx,69m,33k,33p,3g1,3g5,34o,34s,poa,3h8,poc,pog,3gc,cx5,3hb,cwb,3hi,5n4,3j3,3hq,3hw,cy9,cwv,cxa,cz8,3iw,oa4,6a1,cye,3l0,3l2,czd,3ku,6c0,i66,i5w,3me,ai8,3o1,3mu,nap,7g0,7g5,naz,j8v,3ni,h5x,h80,h82,hyg,nf1,oh1,nf2,msm,msl,mso,ikm,g5x,ogq,5eo,ogy,7k5,7k6,7k8,nfb,nff,jny,6hp,6hs,nge,ngi,k18%26vrsn%3DGP_1.27.1.0.charles.0.debug&amp;url=https://www.mxplayer.in/detail/episode/d39914eee9c3d50e21b81e01e8307eaf&amp;unviewed_position_start=1&amp;output=xml_vast3&amp;impl=s&amp;env=vp&amp;gdfp_req=1&amp;ad_rule=0&amp;video_url_to_fetch=https://www.mxplayer.in/detail/episode/d39914eee9c3d50e21b81e01e8307eaf&amp;cue=840000&amp;vad_type=linear&amp;vpos=midroll&amp;pod=8&amp;mridx=7&amp;rmridx=19&amp;pmnd=0&amp;pmxd=60000&amp;pmad=2&amp;vrid=1118784&amp;rdid=2d43e6e5-f1ec-47a8-81b1-10ca1ad1abe1&amp;is_amp=0&amp;dt=1599121523307&amp;idt=416&amp;dlt=1599121522102&amp;correlator=1950702064322958&amp;scor=1681105612848119&amp;sdk_apis=7,8&amp;omid_p=Google1/android.3.11.3&amp;osd=2&amp;vis=1&amp;npa=false&amp;hl=en&amp;frm=0&amp;video_doc_id=d39914eee9c3d50e21b81e01e8307eaf&amp;cmsid=2481704&amp;sdkv=h.3.237.0/n.android.3.11.3/com.mxtech.videoplayer.ad&amp;sdki=405&amp;mpt=google/exo.ext.ima&amp;mpv=2.11.3&amp;sdr=1&amp;eid=44725356&amp;an=com.mxtech.videoplayer.ad&amp;js=ima-android.3.11.3&amp;msid=com.mxtech.videoplayer.ad&amp;u_so=l&amp;is_lat=false&amp;idtype=adid&amp;mv=82161310.com.android.vending&amp;kfa=0&amp;tfcd=0]]>
      </vmap:AdTagURI>
    </vmap:AdSource>
  </vmap:AdBreak>
  <vmap:AdBreak timeOffset="00:16:00.000" breakType="linear" breakId="midroll-8">
    <vmap:AdSource id="midroll-8-ads" allowMultipleAds="true" followRedirects="true">
      <vmap:AdTagURI templateType="vast3">
        <![CDATA[https://pubads.g.doubleclick.net/gampad/ads?slotname=/21723553151/Test/Test_MXPlayer_Video1&amp;sz=400x300%7C640x480&amp;ciu_szs=1440x240&amp;cust_params=sg%3D30b,3g2,3g4,jaz,jbc,2v6,2vh,2vk,2x6,2vt,2vy,5lz,2wl,2wp,5o2,5o8,3iv,jwp,5oa,lkh,5oc,5oe,5of,5og,5op,gau,nr2,iwk,jyq,i5v,o1n,nqv,nqx,o1v,nqy,o1z,ixn,o2a,8gr,ixv,8gv,8gw,3nn,3nq,o3b,7gl,7gm,8it,8k8,8ix,8iy,8l4,8js,mss,jo3,jo8,8ke,8kf,jo9,jnm,jog,3si,cu3,k1m,352,k1w,k2h,8r7,i10,jtl,l85,hr2,80q,80s,80t,l7m,hqv,atp,5mt,oa3,k88,k87,ll7,5od,k8b,k8a,k8d,5q5,k8e,k8j,k8l,k8m,k8r,k8q,i63,o24,o25,o28,o29,k9i,k9h,k9k,iwl,k9l,k9o,k9n,lmf,lme,k9t,k9w,k9v,o1s,o1u,o1t,o1w,o1y,o1x,ocj,o40,3nf,7h6,o50,o57,o3t,hhg,ofb,ka1,ka0,ogx,69m,33k,33p,3g1,3g5,34o,34s,poa,3h8,poc,pog,3gc,cx5,3hb,cwb,3hi,5n4,3j3,3hq,3hw,cy9,cwv,cxa,cz8,3iw,oa4,6a1,cye,3l0,3l2,czd,3ku,6c0,i66,i5w,3me,ai8,3o1,3mu,nap,7g0,7g5,naz,j8v,3ni,h5x,h80,h82,hyg,nf1,oh1,nf2,msm,msl,mso,ikm,g5x,ogq,5eo,ogy,7k5,7k6,7k8,nfb,nff,jny,6hp,6hs,nge,ngi,k18%26vrsn%3DGP_1.27.1.0.charles.0.debug&amp;url=https://www.mxplayer.in/detail/episode/d39914eee9c3d50e21b81e01e8307eaf&amp;unviewed_position_start=1&amp;output=xml_vast3&amp;impl=s&amp;env=vp&amp;gdfp_req=1&amp;ad_rule=0&amp;video_url_to_fetch=https://www.mxplayer.in/detail/episode/d39914eee9c3d50e21b81e01e8307eaf&amp;cue=960000&amp;vad_type=linear&amp;vpos=midroll&amp;pod=9&amp;mridx=8&amp;rmridx=18&amp;pmnd=0&amp;pmxd=60000&amp;pmad=2&amp;vrid=1118784&amp;rdid=2d43e6e5-f1ec-47a8-81b1-10ca1ad1abe1&amp;is_amp=0&amp;dt=1599121523307&amp;idt=416&amp;dlt=1599121522102&amp;correlator=1950702064322958&amp;scor=1681105612848119&amp;sdk_apis=7,8&amp;omid_p=Google1/android.3.11.3&amp;osd=2&amp;vis=1&amp;npa=false&amp;hl=en&amp;frm=0&amp;video_doc_id=d39914eee9c3d50e21b81e01e8307eaf&amp;cmsid=2481704&amp;sdkv=h.3.237.0/n.android.3.11.3/com.mxtech.videoplayer.ad&amp;sdki=405&amp;mpt=google/exo.ext.ima&amp;mpv=2.11.3&amp;sdr=1&amp;eid=44725356&amp;an=com.mxtech.videoplayer.ad&amp;js=ima-android.3.11.3&amp;msid=com.mxtech.videoplayer.ad&amp;u_so=l&amp;is_lat=false&amp;idtype=adid&amp;mv=82161310.com.android.vending&amp;kfa=0&amp;tfcd=0]]>
      </vmap:AdTagURI>
    </vmap:AdSource>
  </vmap:AdBreak>
  <vmap:AdBreak timeOffset="00:18:00.000" breakType="linear" breakId="midroll-9">
    <vmap:AdSource id="midroll-9-ads" allowMultipleAds="true" followRedirects="true">
      <vmap:AdTagURI templateType="vast3">
        <![CDATA[https://pubads.g.doubleclick.net/gampad/ads?slotname=/21723553151/Test/Test_MXPlayer_Video1&amp;sz=400x300%7C640x480&amp;ciu_szs=1440x240&amp;cust_params=sg%3D30b,3g2,3g4,jaz,jbc,2v6,2vh,2vk,2x6,2vt,2vy,5lz,2wl,2wp,5o2,5o8,3iv,jwp,5oa,lkh,5oc,5oe,5of,5og,5op,gau,nr2,iwk,jyq,i5v,o1n,nqv,nqx,o1v,nqy,o1z,ixn,o2a,8gr,ixv,8gv,8gw,3nn,3nq,o3b,7gl,7gm,8it,8k8,8ix,8iy,8l4,8js,mss,jo3,jo8,8ke,8kf,jo9,jnm,jog,3si,cu3,k1m,352,k1w,k2h,8r7,i10,jtl,l85,hr2,80q,80s,80t,l7m,hqv,atp,5mt,oa3,k88,k87,ll7,5od,k8b,k8a,k8d,5q5,k8e,k8j,k8l,k8m,k8r,k8q,i63,o24,o25,o28,o29,k9i,k9h,k9k,iwl,k9l,k9o,k9n,lmf,lme,k9t,k9w,k9v,o1s,o1u,o1t,o1w,o1y,o1x,ocj,o40,3nf,7h6,o50,o57,o3t,hhg,ofb,ka1,ka0,ogx,69m,33k,33p,3g1,3g5,34o,34s,poa,3h8,poc,pog,3gc,cx5,3hb,cwb,3hi,5n4,3j3,3hq,3hw,cy9,cwv,cxa,cz8,3iw,oa4,6a1,cye,3l0,3l2,czd,3ku,6c0,i66,i5w,3me,ai8,3o1,3mu,nap,7g0,7g5,naz,j8v,3ni,h5x,h80,h82,hyg,nf1,oh1,nf2,msm,msl,mso,ikm,g5x,ogq,5eo,ogy,7k5,7k6,7k8,nfb,nff,jny,6hp,6hs,nge,ngi,k18%26vrsn%3DGP_1.27.1.0.charles.0.debug&amp;url=https://www.mxplayer.in/detail/episode/d39914eee9c3d50e21b81e01e8307eaf&amp;unviewed_position_start=1&amp;output=xml_vast3&amp;impl=s&amp;env=vp&amp;gdfp_req=1&amp;ad_rule=0&amp;video_url_to_fetch=https://www.mxplayer.in/detail/episode/d39914eee9c3d50e21b81e01e8307eaf&amp;cue=1080000&amp;vad_type=linear&amp;vpos=midroll&amp;pod=10&amp;mridx=9&amp;rmridx=17&amp;pmnd=0&amp;pmxd=60000&amp;pmad=2&amp;vrid=1118784&amp;rdid=2d43e6e5-f1ec-47a8-81b1-10ca1ad1abe1&amp;is_amp=0&amp;dt=1599121523307&amp;idt=416&amp;dlt=1599121522102&amp;correlator=1950702064322958&amp;scor=1681105612848119&amp;sdk_apis=7,8&amp;omid_p=Google1/android.3.11.3&amp;osd=2&amp;vis=1&amp;npa=false&amp;hl=en&amp;frm=0&amp;video_doc_id=d39914eee9c3d50e21b81e01e8307eaf&amp;cmsid=2481704&amp;sdkv=h.3.237.0/n.android.3.11.3/com.mxtech.videoplayer.ad&amp;sdki=405&amp;mpt=google/exo.ext.ima&amp;mpv=2.11.3&amp;sdr=1&amp;eid=44725356&amp;an=com.mxtech.videoplayer.ad&amp;js=ima-android.3.11.3&amp;msid=com.mxtech.videoplayer.ad&amp;u_so=l&amp;is_lat=false&amp;idtype=adid&amp;mv=82161310.com.android.vending&amp;kfa=0&amp;tfcd=0]]>
      </vmap:AdTagURI>
    </vmap:AdSource>
  </vmap:AdBreak>
  <vmap:AdBreak timeOffset="00:20:00.000" breakType="linear" breakId="midroll-10">
    <vmap:AdSource id="midroll-10-ads" allowMultipleAds="true" followRedirects="true">
      <vmap:AdTagURI templateType="vast3">
        <![CDATA[https://pubads.g.doubleclick.net/gampad/ads?slotname=/21723553151/Test/Test_MXPlayer_Video1&amp;sz=400x300%7C640x480&amp;ciu_szs=1440x240&amp;cust_params=sg%3D30b,3g2,3g4,jaz,jbc,2v6,2vh,2vk,2x6,2vt,2vy,5lz,2wl,2wp,5o2,5o8,3iv,jwp,5oa,lkh,5oc,5oe,5of,5og,5op,gau,nr2,iwk,jyq,i5v,o1n,nqv,nqx,o1v,nqy,o1z,ixn,o2a,8gr,ixv,8gv,8gw,3nn,3nq,o3b,7gl,7gm,8it,8k8,8ix,8iy,8l4,8js,mss,jo3,jo8,8ke,8kf,jo9,jnm,jog,3si,cu3,k1m,352,k1w,k2h,8r7,i10,jtl,l85,hr2,80q,80s,80t,l7m,hqv,atp,5mt,oa3,k88,k87,ll7,5od,k8b,k8a,k8d,5q5,k8e,k8j,k8l,k8m,k8r,k8q,i63,o24,o25,o28,o29,k9i,k9h,k9k,iwl,k9l,k9o,k9n,lmf,lme,k9t,k9w,k9v,o1s,o1u,o1t,o1w,o1y,o1x,ocj,o40,3nf,7h6,o50,o57,o3t,hhg,ofb,ka1,ka0,ogx,69m,33k,33p,3g1,3g5,34o,34s,poa,3h8,poc,pog,3gc,cx5,3hb,cwb,3hi,5n4,3j3,3hq,3hw,cy9,cwv,cxa,cz8,3iw,oa4,6a1,cye,3l0,3l2,czd,3ku,6c0,i66,i5w,3me,ai8,3o1,3mu,nap,7g0,7g5,naz,j8v,3ni,h5x,h80,h82,hyg,nf1,oh1,nf2,msm,msl,mso,ikm,g5x,ogq,5eo,ogy,7k5,7k6,7k8,nfb,nff,jny,6hp,6hs,nge,ngi,k18%26vrsn%3DGP_1.27.1.0.charles.0.debug&amp;url=https://www.mxplayer.in/detail/episode/d39914eee9c3d50e21b81e01e8307eaf&amp;unviewed_position_start=1&amp;output=xml_vast3&amp;impl=s&amp;env=vp&amp;gdfp_req=1&amp;ad_rule=0&amp;video_url_to_fetch=https://www.mxplayer.in/detail/episode/d39914eee9c3d50e21b81e01e8307eaf&amp;cue=1200000&amp;vad_type=linear&amp;vpos=midroll&amp;pod=11&amp;mridx=10&amp;rmridx=16&amp;pmnd=0&amp;pmxd=60000&amp;pmad=2&amp;vrid=1118784&amp;rdid=2d43e6e5-f1ec-47a8-81b1-10ca1ad1abe1&amp;is_amp=0&amp;dt=1599121523307&amp;idt=416&amp;dlt=1599121522102&amp;correlator=1950702064322958&amp;scor=1681105612848119&amp;sdk_apis=7,8&amp;omid_p=Google1/android.3.11.3&amp;osd=2&amp;vis=1&amp;npa=false&amp;hl=en&amp;frm=0&amp;video_doc_id=d39914eee9c3d50e21b81e01e8307eaf&amp;cmsid=2481704&amp;sdkv=h.3.237.0/n.android.3.11.3/com.mxtech.videoplayer.ad&amp;sdki=405&amp;mpt=google/exo.ext.ima&amp;mpv=2.11.3&amp;sdr=1&amp;eid=44725356&amp;an=com.mxtech.videoplayer.ad&amp;js=ima-android.3.11.3&amp;msid=com.mxtech.videoplayer.ad&amp;u_so=l&amp;is_lat=false&amp;idtype=adid&amp;mv=82161310.com.android.vending&amp;kfa=0&amp;tfcd=0]]>
      </vmap:AdTagURI>
    </vmap:AdSource>
  </vmap:AdBreak>
  <vmap:AdBreak timeOffset="00:22:00.000" breakType="linear" breakId="midroll-11">
    <vmap:AdSource id="midroll-11-ads" allowMultipleAds="true" followRedirects="true">
      <vmap:AdTagURI templateType="vast3">
        <![CDATA[https://pubads.g.doubleclick.net/gampad/ads?slotname=/21723553151/Test/Test_MXPlayer_Video1&amp;sz=400x300%7C640x480&amp;ciu_szs=1440x240&amp;cust_params=sg%3D30b,3g2,3g4,jaz,jbc,2v6,2vh,2vk,2x6,2vt,2vy,5lz,2wl,2wp,5o2,5o8,3iv,jwp,5oa,lkh,5oc,5oe,5of,5og,5op,gau,nr2,iwk,jyq,i5v,o1n,nqv,nqx,o1v,nqy,o1z,ixn,o2a,8gr,ixv,8gv,8gw,3nn,3nq,o3b,7gl,7gm,8it,8k8,8ix,8iy,8l4,8js,mss,jo3,jo8,8ke,8kf,jo9,jnm,jog,3si,cu3,k1m,352,k1w,k2h,8r7,i10,jtl,l85,hr2,80q,80s,80t,l7m,hqv,atp,5mt,oa3,k88,k87,ll7,5od,k8b,k8a,k8d,5q5,k8e,k8j,k8l,k8m,k8r,k8q,i63,o24,o25,o28,o29,k9i,k9h,k9k,iwl,k9l,k9o,k9n,lmf,lme,k9t,k9w,k9v,o1s,o1u,o1t,o1w,o1y,o1x,ocj,o40,3nf,7h6,o50,o57,o3t,hhg,ofb,ka1,ka0,ogx,69m,33k,33p,3g1,3g5,34o,34s,poa,3h8,poc,pog,3gc,cx5,3hb,cwb,3hi,5n4,3j3,3hq,3hw,cy9,cwv,cxa,cz8,3iw,oa4,6a1,cye,3l0,3l2,czd,3ku,6c0,i66,i5w,3me,ai8,3o1,3mu,nap,7g0,7g5,naz,j8v,3ni,h5x,h80,h82,hyg,nf1,oh1,nf2,msm,msl,mso,ikm,g5x,ogq,5eo,ogy,7k5,7k6,7k8,nfb,nff,jny,6hp,6hs,nge,ngi,k18%26vrsn%3DGP_1.27.1.0.charles.0.debug&amp;url=https://www.mxplayer.in/detail/episode/d39914eee9c3d50e21b81e01e8307eaf&amp;unviewed_position_start=1&amp;output=xml_vast3&amp;impl=s&amp;env=vp&amp;gdfp_req=1&amp;ad_rule=0&amp;video_url_to_fetch=https://www.mxplayer.in/detail/episode/d39914eee9c3d50e21b81e01e8307eaf&amp;cue=1320000&amp;vad_type=linear&amp;vpos=midroll&amp;pod=12&amp;mridx=11&amp;rmridx=15&amp;pmnd=0&amp;pmxd=60000&amp;pmad=2&amp;vrid=1118784&amp;rdid=2d43e6e5-f1ec-47a8-81b1-10ca1ad1abe1&amp;is_amp=0&amp;dt=1599121523307&amp;idt=416&amp;dlt=1599121522102&amp;correlator=1950702064322958&amp;scor=1681105612848119&amp;sdk_apis=7,8&amp;omid_p=Google1/android.3.11.3&amp;osd=2&amp;vis=1&amp;npa=false&amp;hl=en&amp;frm=0&amp;video_doc_id=d39914eee9c3d50e21b81e01e8307eaf&amp;cmsid=2481704&amp;sdkv=h.3.237.0/n.android.3.11.3/com.mxtech.videoplayer.ad&amp;sdki=405&amp;mpt=google/exo.ext.ima&amp;mpv=2.11.3&amp;sdr=1&amp;eid=44725356&amp;an=com.mxtech.videoplayer.ad&amp;js=ima-android.3.11.3&amp;msid=com.mxtech.videoplayer.ad&amp;u_so=l&amp;is_lat=false&amp;idtype=adid&amp;mv=82161310.com.android.vending&amp;kfa=0&amp;tfcd=0]]>
      </vmap:AdTagURI>
    </vmap:AdSource>
  </vmap:AdBreak>
  <vmap:AdBreak timeOffset="00:24:00.000" breakType="linear" breakId="midroll-12">
    <vmap:AdSource id="midroll-12-ads" allowMultipleAds="true" followRedirects="true">
      <vmap:AdTagURI templateType="vast3">
        <![CDATA[https://pubads.g.doubleclick.net/gampad/ads?slotname=/21723553151/Test/Test_MXPlayer_Video1&amp;sz=400x300%7C640x480&amp;ciu_szs=1440x240&amp;cust_params=sg%3D30b,3g2,3g4,jaz,jbc,2v6,2vh,2vk,2x6,2vt,2vy,5lz,2wl,2wp,5o2,5o8,3iv,jwp,5oa,lkh,5oc,5oe,5of,5og,5op,gau,nr2,iwk,jyq,i5v,o1n,nqv,nqx,o1v,nqy,o1z,ixn,o2a,8gr,ixv,8gv,8gw,3nn,3nq,o3b,7gl,7gm,8it,8k8,8ix,8iy,8l4,8js,mss,jo3,jo8,8ke,8kf,jo9,jnm,jog,3si,cu3,k1m,352,k1w,k2h,8r7,i10,jtl,l85,hr2,80q,80s,80t,l7m,hqv,atp,5mt,oa3,k88,k87,ll7,5od,k8b,k8a,k8d,5q5,k8e,k8j,k8l,k8m,k8r,k8q,i63,o24,o25,o28,o29,k9i,k9h,k9k,iwl,k9l,k9o,k9n,lmf,lme,k9t,k9w,k9v,o1s,o1u,o1t,o1w,o1y,o1x,ocj,o40,3nf,7h6,o50,o57,o3t,hhg,ofb,ka1,ka0,ogx,69m,33k,33p,3g1,3g5,34o,34s,poa,3h8,poc,pog,3gc,cx5,3hb,cwb,3hi,5n4,3j3,3hq,3hw,cy9,cwv,cxa,cz8,3iw,oa4,6a1,cye,3l0,3l2,czd,3ku,6c0,i66,i5w,3me,ai8,3o1,3mu,nap,7g0,7g5,naz,j8v,3ni,h5x,h80,h82,hyg,nf1,oh1,nf2,msm,msl,mso,ikm,g5x,ogq,5eo,ogy,7k5,7k6,7k8,nfb,nff,jny,6hp,6hs,nge,ngi,k18%26vrsn%3DGP_1.27.1.0.charles.0.debug&amp;url=https://www.mxplayer.in/detail/episode/d39914eee9c3d50e21b81e01e8307eaf&amp;unviewed_position_start=1&amp;output=xml_vast3&amp;impl=s&amp;env=vp&amp;gdfp_req=1&amp;ad_rule=0&amp;video_url_to_fetch=https://www.mxplayer.in/detail/episode/d39914eee9c3d50e21b81e01e8307eaf&amp;cue=1440000&amp;vad_type=linear&amp;vpos=midroll&amp;pod=13&amp;mridx=12&amp;rmridx=14&amp;pmnd=0&amp;pmxd=60000&amp;pmad=2&amp;vrid=1118784&amp;rdid=2d43e6e5-f1ec-47a8-81b1-10ca1ad1abe1&amp;is_amp=0&amp;dt=1599121523307&amp;idt=416&amp;dlt=1599121522102&amp;correlator=1950702064322958&amp;scor=1681105612848119&amp;sdk_apis=7,8&amp;omid_p=Google1/android.3.11.3&amp;osd=2&amp;vis=1&amp;npa=false&amp;hl=en&amp;frm=0&amp;video_doc_id=d39914eee9c3d50e21b81e01e8307eaf&amp;cmsid=2481704&amp;sdkv=h.3.237.0/n.android.3.11.3/com.mxtech.videoplayer.ad&amp;sdki=405&amp;mpt=google/exo.ext.ima&amp;mpv=2.11.3&amp;sdr=1&amp;eid=44725356&amp;an=com.mxtech.videoplayer.ad&amp;js=ima-android.3.11.3&amp;msid=com.mxtech.videoplayer.ad&amp;u_so=l&amp;is_lat=false&amp;idtype=adid&amp;mv=82161310.com.android.vending&amp;kfa=0&amp;tfcd=0]]>
      </vmap:AdTagURI>
    </vmap:AdSource>
  </vmap:AdBreak>
  <vmap:AdBreak timeOffset="00:26:00.000" breakType="linear" breakId="midroll-13">
    <vmap:AdSource id="midroll-13-ads" allowMultipleAds="true" followRedirects="true">
      <vmap:AdTagURI templateType="vast3">
        <![CDATA[https://pubads.g.doubleclick.net/gampad/ads?slotname=/21723553151/Test/Test_MXPlayer_Video1&amp;sz=400x300%7C640x480&amp;ciu_szs=1440x240&amp;cust_params=sg%3D30b,3g2,3g4,jaz,jbc,2v6,2vh,2vk,2x6,2vt,2vy,5lz,2wl,2wp,5o2,5o8,3iv,jwp,5oa,lkh,5oc,5oe,5of,5og,5op,gau,nr2,iwk,jyq,i5v,o1n,nqv,nqx,o1v,nqy,o1z,ixn,o2a,8gr,ixv,8gv,8gw,3nn,3nq,o3b,7gl,7gm,8it,8k8,8ix,8iy,8l4,8js,mss,jo3,jo8,8ke,8kf,jo9,jnm,jog,3si,cu3,k1m,352,k1w,k2h,8r7,i10,jtl,l85,hr2,80q,80s,80t,l7m,hqv,atp,5mt,oa3,k88,k87,ll7,5od,k8b,k8a,k8d,5q5,k8e,k8j,k8l,k8m,k8r,k8q,i63,o24,o25,o28,o29,k9i,k9h,k9k,iwl,k9l,k9o,k9n,lmf,lme,k9t,k9w,k9v,o1s,o1u,o1t,o1w,o1y,o1x,ocj,o40,3nf,7h6,o50,o57,o3t,hhg,ofb,ka1,ka0,ogx,69m,33k,33p,3g1,3g5,34o,34s,poa,3h8,poc,pog,3gc,cx5,3hb,cwb,3hi,5n4,3j3,3hq,3hw,cy9,cwv,cxa,cz8,3iw,oa4,6a1,cye,3l0,3l2,czd,3ku,6c0,i66,i5w,3me,ai8,3o1,3mu,nap,7g0,7g5,naz,j8v,3ni,h5x,h80,h82,hyg,nf1,oh1,nf2,msm,msl,mso,ikm,g5x,ogq,5eo,ogy,7k5,7k6,7k8,nfb,nff,jny,6hp,6hs,nge,ngi,k18%26vrsn%3DGP_1.27.1.0.charles.0.debug&amp;url=https://www.mxplayer.in/detail/episode/d39914eee9c3d50e21b81e01e8307eaf&amp;unviewed_position_start=1&amp;output=xml_vast3&amp;impl=s&amp;env=vp&amp;gdfp_req=1&amp;ad_rule=0&amp;video_url_to_fetch=https://www.mxplayer.in/detail/episode/d39914eee9c3d50e21b81e01e8307eaf&amp;cue=1560000&amp;vad_type=linear&amp;vpos=midroll&amp;pod=14&amp;mridx=13&amp;rmridx=13&amp;pmnd=0&amp;pmxd=60000&amp;pmad=2&amp;vrid=1118784&amp;rdid=2d43e6e5-f1ec-47a8-81b1-10ca1ad1abe1&amp;is_amp=0&amp;dt=1599121523307&amp;idt=416&amp;dlt=1599121522102&amp;correlator=1950702064322958&amp;scor=1681105612848119&amp;sdk_apis=7,8&amp;omid_p=Google1/android.3.11.3&amp;osd=2&amp;vis=1&amp;npa=false&amp;hl=en&amp;frm=0&amp;video_doc_id=d39914eee9c3d50e21b81e01e8307eaf&amp;cmsid=2481704&amp;sdkv=h.3.237.0/n.android.3.11.3/com.mxtech.videoplayer.ad&amp;sdki=405&amp;mpt=google/exo.ext.ima&amp;mpv=2.11.3&amp;sdr=1&amp;eid=44725356&amp;an=com.mxtech.videoplayer.ad&amp;js=ima-android.3.11.3&amp;msid=com.mxtech.videoplayer.ad&amp;u_so=l&amp;is_lat=false&amp;idtype=adid&amp;mv=82161310.com.android.vending&amp;kfa=0&amp;tfcd=0]]>
      </vmap:AdTagURI>
    </vmap:AdSource>
  </vmap:AdBreak>
  <vmap:AdBreak timeOffset="00:28:00.000" breakType="linear" breakId="midroll-14">
    <vmap:AdSource id="midroll-14-ads" allowMultipleAds="true" followRedirects="true">
      <vmap:AdTagURI templateType="vast3">
        <![CDATA[https://pubads.g.doubleclick.net/gampad/ads?slotname=/21723553151/Test/Test_MXPlayer_Video1&amp;sz=400x300%7C640x480&amp;ciu_szs=1440x240&amp;cust_params=sg%3D30b,3g2,3g4,jaz,jbc,2v6,2vh,2vk,2x6,2vt,2vy,5lz,2wl,2wp,5o2,5o8,3iv,jwp,5oa,lkh,5oc,5oe,5of,5og,5op,gau,nr2,iwk,jyq,i5v,o1n,nqv,nqx,o1v,nqy,o1z,ixn,o2a,8gr,ixv,8gv,8gw,3nn,3nq,o3b,7gl,7gm,8it,8k8,8ix,8iy,8l4,8js,mss,jo3,jo8,8ke,8kf,jo9,jnm,jog,3si,cu3,k1m,352,k1w,k2h,8r7,i10,jtl,l85,hr2,80q,80s,80t,l7m,hqv,atp,5mt,oa3,k88,k87,ll7,5od,k8b,k8a,k8d,5q5,k8e,k8j,k8l,k8m,k8r,k8q,i63,o24,o25,o28,o29,k9i,k9h,k9k,iwl,k9l,k9o,k9n,lmf,lme,k9t,k9w,k9v,o1s,o1u,o1t,o1w,o1y,o1x,ocj,o40,3nf,7h6,o50,o57,o3t,hhg,ofb,ka1,ka0,ogx,69m,33k,33p,3g1,3g5,34o,34s,poa,3h8,poc,pog,3gc,cx5,3hb,cwb,3hi,5n4,3j3,3hq,3hw,cy9,cwv,cxa,cz8,3iw,oa4,6a1,cye,3l0,3l2,czd,3ku,6c0,i66,i5w,3me,ai8,3o1,3mu,nap,7g0,7g5,naz,j8v,3ni,h5x,h80,h82,hyg,nf1,oh1,nf2,msm,msl,mso,ikm,g5x,ogq,5eo,ogy,7k5,7k6,7k8,nfb,nff,jny,6hp,6hs,nge,ngi,k18%26vrsn%3DGP_1.27.1.0.charles.0.debug&amp;url=https://www.mxplayer.in/detail/episode/d39914eee9c3d50e21b81e01e8307eaf&amp;unviewed_position_start=1&amp;output=xml_vast3&amp;impl=s&amp;env=vp&amp;gdfp_req=1&amp;ad_rule=0&amp;video_url_to_fetch=https://www.mxplayer.in/detail/episode/d39914eee9c3d50e21b81e01e8307eaf&amp;cue=1680000&amp;vad_type=linear&amp;vpos=midroll&amp;pod=15&amp;mridx=14&amp;rmridx=12&amp;pmnd=0&amp;pmxd=60000&amp;pmad=2&amp;vrid=1118784&amp;rdid=2d43e6e5-f1ec-47a8-81b1-10ca1ad1abe1&amp;is_amp=0&amp;dt=1599121523307&amp;idt=416&amp;dlt=1599121522102&amp;correlator=1950702064322958&amp;scor=1681105612848119&amp;sdk_apis=7,8&amp;omid_p=Google1/android.3.11.3&amp;osd=2&amp;vis=1&amp;npa=false&amp;hl=en&amp;frm=0&amp;video_doc_id=d39914eee9c3d50e21b81e01e8307eaf&amp;cmsid=2481704&amp;sdkv=h.3.237.0/n.android.3.11.3/com.mxtech.videoplayer.ad&amp;sdki=405&amp;mpt=google/exo.ext.ima&amp;mpv=2.11.3&amp;sdr=1&amp;eid=44725356&amp;an=com.mxtech.videoplayer.ad&amp;js=ima-android.3.11.3&amp;msid=com.mxtech.videoplayer.ad&amp;u_so=l&amp;is_lat=false&amp;idtype=adid&amp;mv=82161310.com.android.vending&amp;kfa=0&amp;tfcd=0]]>
      </vmap:AdTagURI>
    </vmap:AdSource>
  </vmap:AdBreak>
  <vmap:AdBreak timeOffset="00:30:00.000" breakType="linear" breakId="midroll-15">
    <vmap:AdSource id="midroll-15-ads" allowMultipleAds="true" followRedirects="true">
      <vmap:AdTagURI templateType="vast3">
        <![CDATA[https://pubads.g.doubleclick.net/gampad/ads?slotname=/21723553151/Test/Test_MXPlayer_Video1&amp;sz=400x300%7C640x480&amp;ciu_szs=1440x240&amp;cust_params=sg%3D30b,3g2,3g4,jaz,jbc,2v6,2vh,2vk,2x6,2vt,2vy,5lz,2wl,2wp,5o2,5o8,3iv,jwp,5oa,lkh,5oc,5oe,5of,5og,5op,gau,nr2,iwk,jyq,i5v,o1n,nqv,nqx,o1v,nqy,o1z,ixn,o2a,8gr,ixv,8gv,8gw,3nn,3nq,o3b,7gl,7gm,8it,8k8,8ix,8iy,8l4,8js,mss,jo3,jo8,8ke,8kf,jo9,jnm,jog,3si,cu3,k1m,352,k1w,k2h,8r7,i10,jtl,l85,hr2,80q,80s,80t,l7m,hqv,atp,5mt,oa3,k88,k87,ll7,5od,k8b,k8a,k8d,5q5,k8e,k8j,k8l,k8m,k8r,k8q,i63,o24,o25,o28,o29,k9i,k9h,k9k,iwl,k9l,k9o,k9n,lmf,lme,k9t,k9w,k9v,o1s,o1u,o1t,o1w,o1y,o1x,ocj,o40,3nf,7h6,o50,o57,o3t,hhg,ofb,ka1,ka0,ogx,69m,33k,33p,3g1,3g5,34o,34s,poa,3h8,poc,pog,3gc,cx5,3hb,cwb,3hi,5n4,3j3,3hq,3hw,cy9,cwv,cxa,cz8,3iw,oa4,6a1,cye,3l0,3l2,czd,3ku,6c0,i66,i5w,3me,ai8,3o1,3mu,nap,7g0,7g5,naz,j8v,3ni,h5x,h80,h82,hyg,nf1,oh1,nf2,msm,msl,mso,ikm,g5x,ogq,5eo,ogy,7k5,7k6,7k8,nfb,nff,jny,6hp,6hs,nge,ngi,k18%26vrsn%3DGP_1.27.1.0.charles.0.debug&amp;url=https://www.mxplayer.in/detail/episode/d39914eee9c3d50e21b81e01e8307eaf&amp;unviewed_position_start=1&amp;output=xml_vast3&amp;impl=s&amp;env=vp&amp;gdfp_req=1&amp;ad_rule=0&amp;video_url_to_fetch=https://www.mxplayer.in/detail/episode/d39914eee9c3d50e21b81e01e8307eaf&amp;cue=1800000&amp;vad_type=linear&amp;vpos=midroll&amp;pod=16&amp;mridx=15&amp;rmridx=11&amp;pmnd=0&amp;pmxd=60000&amp;pmad=2&amp;vrid=1118784&amp;rdid=2d43e6e5-f1ec-47a8-81b1-10ca1ad1abe1&amp;is_amp=0&amp;dt=1599121523307&amp;idt=416&amp;dlt=1599121522102&amp;correlator=1950702064322958&amp;scor=1681105612848119&amp;sdk_apis=7,8&amp;omid_p=Google1/android.3.11.3&amp;osd=2&amp;vis=1&amp;npa=false&amp;hl=en&amp;frm=0&amp;video_doc_id=d39914eee9c3d50e21b81e01e8307eaf&amp;cmsid=2481704&amp;sdkv=h.3.237.0/n.android.3.11.3/com.mxtech.videoplayer.ad&amp;sdki=405&amp;mpt=google/exo.ext.ima&amp;mpv=2.11.3&amp;sdr=1&amp;eid=44725356&amp;an=com.mxtech.videoplayer.ad&amp;js=ima-android.3.11.3&amp;msid=com.mxtech.videoplayer.ad&amp;u_so=l&amp;is_lat=false&amp;idtype=adid&amp;mv=82161310.com.android.vending&amp;kfa=0&amp;tfcd=0]]>
      </vmap:AdTagURI>
    </vmap:AdSource>
  </vmap:AdBreak>
  <vmap:AdBreak timeOffset="00:32:00.000" breakType="linear" breakId="midroll-16">
    <vmap:AdSource id="midroll-16-ads" allowMultipleAds="true" followRedirects="true">
      <vmap:AdTagURI templateType="vast3">
        <![CDATA[https://pubads.g.doubleclick.net/gampad/ads?slotname=/21723553151/Test/Test_MXPlayer_Video1&amp;sz=400x300%7C640x480&amp;ciu_szs=1440x240&amp;cust_params=sg%3D30b,3g2,3g4,jaz,jbc,2v6,2vh,2vk,2x6,2vt,2vy,5lz,2wl,2wp,5o2,5o8,3iv,jwp,5oa,lkh,5oc,5oe,5of,5og,5op,gau,nr2,iwk,jyq,i5v,o1n,nqv,nqx,o1v,nqy,o1z,ixn,o2a,8gr,ixv,8gv,8gw,3nn,3nq,o3b,7gl,7gm,8it,8k8,8ix,8iy,8l4,8js,mss,jo3,jo8,8ke,8kf,jo9,jnm,jog,3si,cu3,k1m,352,k1w,k2h,8r7,i10,jtl,l85,hr2,80q,80s,80t,l7m,hqv,atp,5mt,oa3,k88,k87,ll7,5od,k8b,k8a,k8d,5q5,k8e,k8j,k8l,k8m,k8r,k8q,i63,o24,o25,o28,o29,k9i,k9h,k9k,iwl,k9l,k9o,k9n,lmf,lme,k9t,k9w,k9v,o1s,o1u,o1t,o1w,o1y,o1x,ocj,o40,3nf,7h6,o50,o57,o3t,hhg,ofb,ka1,ka0,ogx,69m,33k,33p,3g1,3g5,34o,34s,poa,3h8,poc,pog,3gc,cx5,3hb,cwb,3hi,5n4,3j3,3hq,3hw,cy9,cwv,cxa,cz8,3iw,oa4,6a1,cye,3l0,3l2,czd,3ku,6c0,i66,i5w,3me,ai8,3o1,3mu,nap,7g0,7g5,naz,j8v,3ni,h5x,h80,h82,hyg,nf1,oh1,nf2,msm,msl,mso,ikm,g5x,ogq,5eo,ogy,7k5,7k6,7k8,nfb,nff,jny,6hp,6hs,nge,ngi,k18%26vrsn%3DGP_1.27.1.0.charles.0.debug&amp;url=https://www.mxplayer.in/detail/episode/d39914eee9c3d50e21b81e01e8307eaf&amp;unviewed_position_start=1&amp;output=xml_vast3&amp;impl=s&amp;env=vp&amp;gdfp_req=1&amp;ad_rule=0&amp;video_url_to_fetch=https://www.mxplayer.in/detail/episode/d39914eee9c3d50e21b81e01e8307eaf&amp;cue=1920000&amp;vad_type=linear&amp;vpos=midroll&amp;pod=17&amp;mridx=16&amp;rmridx=10&amp;pmnd=0&amp;pmxd=60000&amp;pmad=2&amp;vrid=1118784&amp;rdid=2d43e6e5-f1ec-47a8-81b1-10ca1ad1abe1&amp;is_amp=0&amp;dt=1599121523307&amp;idt=416&amp;dlt=1599121522102&amp;correlator=1950702064322958&amp;scor=1681105612848119&amp;sdk_apis=7,8&amp;omid_p=Google1/android.3.11.3&amp;osd=2&amp;vis=1&amp;npa=false&amp;hl=en&amp;frm=0&amp;video_doc_id=d39914eee9c3d50e21b81e01e8307eaf&amp;cmsid=2481704&amp;sdkv=h.3.237.0/n.android.3.11.3/com.mxtech.videoplayer.ad&amp;sdki=405&amp;mpt=google/exo.ext.ima&amp;mpv=2.11.3&amp;sdr=1&amp;eid=44725356&amp;an=com.mxtech.videoplayer.ad&amp;js=ima-android.3.11.3&amp;msid=com.mxtech.videoplayer.ad&amp;u_so=l&amp;is_lat=false&amp;idtype=adid&amp;mv=82161310.com.android.vending&amp;kfa=0&amp;tfcd=0]]>
      </vmap:AdTagURI>
    </vmap:AdSource>
  </vmap:AdBreak>
  <vmap:AdBreak timeOffset="00:34:00.000" breakType="linear" breakId="midroll-17">
    <vmap:AdSource id="midroll-17-ads" allowMultipleAds="true" followRedirects="true">
      <vmap:AdTagURI templateType="vast3">
        <![CDATA[https://pubads.g.doubleclick.net/gampad/ads?slotname=/21723553151/Test/Test_MXPlayer_Video1&amp;sz=400x300%7C640x480&amp;ciu_szs=1440x240&amp;cust_params=sg%3D30b,3g2,3g4,jaz,jbc,2v6,2vh,2vk,2x6,2vt,2vy,5lz,2wl,2wp,5o2,5o8,3iv,jwp,5oa,lkh,5oc,5oe,5of,5og,5op,gau,nr2,iwk,jyq,i5v,o1n,nqv,nqx,o1v,nqy,o1z,ixn,o2a,8gr,ixv,8gv,8gw,3nn,3nq,o3b,7gl,7gm,8it,8k8,8ix,8iy,8l4,8js,mss,jo3,jo8,8ke,8kf,jo9,jnm,jog,3si,cu3,k1m,352,k1w,k2h,8r7,i10,jtl,l85,hr2,80q,80s,80t,l7m,hqv,atp,5mt,oa3,k88,k87,ll7,5od,k8b,k8a,k8d,5q5,k8e,k8j,k8l,k8m,k8r,k8q,i63,o24,o25,o28,o29,k9i,k9h,k9k,iwl,k9l,k9o,k9n,lmf,lme,k9t,k9w,k9v,o1s,o1u,o1t,o1w,o1y,o1x,ocj,o40,3nf,7h6,o50,o57,o3t,hhg,ofb,ka1,ka0,ogx,69m,33k,33p,3g1,3g5,34o,34s,poa,3h8,poc,pog,3gc,cx5,3hb,cwb,3hi,5n4,3j3,3hq,3hw,cy9,cwv,cxa,cz8,3iw,oa4,6a1,cye,3l0,3l2,czd,3ku,6c0,i66,i5w,3me,ai8,3o1,3mu,nap,7g0,7g5,naz,j8v,3ni,h5x,h80,h82,hyg,nf1,oh1,nf2,msm,msl,mso,ikm,g5x,ogq,5eo,ogy,7k5,7k6,7k8,nfb,nff,jny,6hp,6hs,nge,ngi,k18%26vrsn%3DGP_1.27.1.0.charles.0.debug&amp;url=https://www.mxplayer.in/detail/episode/d39914eee9c3d50e21b81e01e8307eaf&amp;unviewed_position_start=1&amp;output=xml_vast3&amp;impl=s&amp;env=vp&amp;gdfp_req=1&amp;ad_rule=0&amp;video_url_to_fetch=https://www.mxplayer.in/detail/episode/d39914eee9c3d50e21b81e01e8307eaf&amp;cue=2040000&amp;vad_type=linear&amp;vpos=midroll&amp;pod=18&amp;mridx=17&amp;rmridx=9&amp;pmnd=0&amp;pmxd=60000&amp;pmad=2&amp;vrid=1118784&amp;rdid=2d43e6e5-f1ec-47a8-81b1-10ca1ad1abe1&amp;is_amp=0&amp;dt=1599121523307&amp;idt=416&amp;dlt=1599121522102&amp;correlator=1950702064322958&amp;scor=1681105612848119&amp;sdk_apis=7,8&amp;omid_p=Google1/android.3.11.3&amp;osd=2&amp;vis=1&amp;npa=false&amp;hl=en&amp;frm=0&amp;video_doc_id=d39914eee9c3d50e21b81e01e8307eaf&amp;cmsid=2481704&amp;sdkv=h.3.237.0/n.android.3.11.3/com.mxtech.videoplayer.ad&amp;sdki=405&amp;mpt=google/exo.ext.ima&amp;mpv=2.11.3&amp;sdr=1&amp;eid=44725356&amp;an=com.mxtech.videoplayer.ad&amp;js=ima-android.3.11.3&amp;msid=com.mxtech.videoplayer.ad&amp;u_so=l&amp;is_lat=false&amp;idtype=adid&amp;mv=82161310.com.android.vending&amp;kfa=0&amp;tfcd=0]]>
      </vmap:AdTagURI>
    </vmap:AdSource>
  </vmap:AdBreak>
  <vmap:AdBreak timeOffset="00:36:00.000" breakType="linear" breakId="midroll-18">
    <vmap:AdSource id="midroll-18-ads" allowMultipleAds="true" followRedirects="true">
      <vmap:AdTagURI templateType="vast3">
        <![CDATA[https://pubads.g.doubleclick.net/gampad/ads?slotname=/21723553151/Test/Test_MXPlayer_Video1&amp;sz=400x300%7C640x480&amp;ciu_szs=1440x240&amp;cust_params=sg%3D30b,3g2,3g4,jaz,jbc,2v6,2vh,2vk,2x6,2vt,2vy,5lz,2wl,2wp,5o2,5o8,3iv,jwp,5oa,lkh,5oc,5oe,5of,5og,5op,gau,nr2,iwk,jyq,i5v,o1n,nqv,nqx,o1v,nqy,o1z,ixn,o2a,8gr,ixv,8gv,8gw,3nn,3nq,o3b,7gl,7gm,8it,8k8,8ix,8iy,8l4,8js,mss,jo3,jo8,8ke,8kf,jo9,jnm,jog,3si,cu3,k1m,352,k1w,k2h,8r7,i10,jtl,l85,hr2,80q,80s,80t,l7m,hqv,atp,5mt,oa3,k88,k87,ll7,5od,k8b,k8a,k8d,5q5,k8e,k8j,k8l,k8m,k8r,k8q,i63,o24,o25,o28,o29,k9i,k9h,k9k,iwl,k9l,k9o,k9n,lmf,lme,k9t,k9w,k9v,o1s,o1u,o1t,o1w,o1y,o1x,ocj,o40,3nf,7h6,o50,o57,o3t,hhg,ofb,ka1,ka0,ogx,69m,33k,33p,3g1,3g5,34o,34s,poa,3h8,poc,pog,3gc,cx5,3hb,cwb,3hi,5n4,3j3,3hq,3hw,cy9,cwv,cxa,cz8,3iw,oa4,6a1,cye,3l0,3l2,czd,3ku,6c0,i66,i5w,3me,ai8,3o1,3mu,nap,7g0,7g5,naz,j8v,3ni,h5x,h80,h82,hyg,nf1,oh1,nf2,msm,msl,mso,ikm,g5x,ogq,5eo,ogy,7k5,7k6,7k8,nfb,nff,jny,6hp,6hs,nge,ngi,k18%26vrsn%3DGP_1.27.1.0.charles.0.debug&amp;url=https://www.mxplayer.in/detail/episode/d39914eee9c3d50e21b81e01e8307eaf&amp;unviewed_position_start=1&amp;output=xml_vast3&amp;impl=s&amp;env=vp&amp;gdfp_req=1&amp;ad_rule=0&amp;video_url_to_fetch=https://www.mxplayer.in/detail/episode/d39914eee9c3d50e21b81e01e8307eaf&amp;cue=2160000&amp;vad_type=linear&amp;vpos=midroll&amp;pod=19&amp;mridx=18&amp;rmridx=8&amp;pmnd=0&amp;pmxd=60000&amp;pmad=2&amp;vrid=1118784&amp;rdid=2d43e6e5-f1ec-47a8-81b1-10ca1ad1abe1&amp;is_amp=0&amp;dt=1599121523307&amp;idt=416&amp;dlt=1599121522102&amp;correlator=1950702064322958&amp;scor=1681105612848119&amp;sdk_apis=7,8&amp;omid_p=Google1/android.3.11.3&amp;osd=2&amp;vis=1&amp;npa=false&amp;hl=en&amp;frm=0&amp;video_doc_id=d39914eee9c3d50e21b81e01e8307eaf&amp;cmsid=2481704&amp;sdkv=h.3.237.0/n.android.3.11.3/com.mxtech.videoplayer.ad&amp;sdki=405&amp;mpt=google/exo.ext.ima&amp;mpv=2.11.3&amp;sdr=1&amp;eid=44725356&amp;an=com.mxtech.videoplayer.ad&amp;js=ima-android.3.11.3&amp;msid=com.mxtech.videoplayer.ad&amp;u_so=l&amp;is_lat=false&amp;idtype=adid&amp;mv=82161310.com.android.vending&amp;kfa=0&amp;tfcd=0]]>
      </vmap:AdTagURI>
    </vmap:AdSource>
  </vmap:AdBreak>
  <vmap:AdBreak timeOffset="00:38:00.000" breakType="linear" breakId="midroll-19">
    <vmap:AdSource id="midroll-19-ads" allowMultipleAds="true" followRedirects="true">
      <vmap:AdTagURI templateType="vast3">
        <![CDATA[https://pubads.g.doubleclick.net/gampad/ads?slotname=/21723553151/Test/Test_MXPlayer_Video1&amp;sz=400x300%7C640x480&amp;ciu_szs=1440x240&amp;cust_params=sg%3D30b,3g2,3g4,jaz,jbc,2v6,2vh,2vk,2x6,2vt,2vy,5lz,2wl,2wp,5o2,5o8,3iv,jwp,5oa,lkh,5oc,5oe,5of,5og,5op,gau,nr2,iwk,jyq,i5v,o1n,nqv,nqx,o1v,nqy,o1z,ixn,o2a,8gr,ixv,8gv,8gw,3nn,3nq,o3b,7gl,7gm,8it,8k8,8ix,8iy,8l4,8js,mss,jo3,jo8,8ke,8kf,jo9,jnm,jog,3si,cu3,k1m,352,k1w,k2h,8r7,i10,jtl,l85,hr2,80q,80s,80t,l7m,hqv,atp,5mt,oa3,k88,k87,ll7,5od,k8b,k8a,k8d,5q5,k8e,k8j,k8l,k8m,k8r,k8q,i63,o24,o25,o28,o29,k9i,k9h,k9k,iwl,k9l,k9o,k9n,lmf,lme,k9t,k9w,k9v,o1s,o1u,o1t,o1w,o1y,o1x,ocj,o40,3nf,7h6,o50,o57,o3t,hhg,ofb,ka1,ka0,ogx,69m,33k,33p,3g1,3g5,34o,34s,poa,3h8,poc,pog,3gc,cx5,3hb,cwb,3hi,5n4,3j3,3hq,3hw,cy9,cwv,cxa,cz8,3iw,oa4,6a1,cye,3l0,3l2,czd,3ku,6c0,i66,i5w,3me,ai8,3o1,3mu,nap,7g0,7g5,naz,j8v,3ni,h5x,h80,h82,hyg,nf1,oh1,nf2,msm,msl,mso,ikm,g5x,ogq,5eo,ogy,7k5,7k6,7k8,nfb,nff,jny,6hp,6hs,nge,ngi,k18%26vrsn%3DGP_1.27.1.0.charles.0.debug&amp;url=https://www.mxplayer.in/detail/episode/d39914eee9c3d50e21b81e01e8307eaf&amp;unviewed_position_start=1&amp;output=xml_vast3&amp;impl=s&amp;env=vp&amp;gdfp_req=1&amp;ad_rule=0&amp;video_url_to_fetch=https://www.mxplayer.in/detail/episode/d39914eee9c3d50e21b81e01e8307eaf&amp;cue=2280000&amp;vad_type=linear&amp;vpos=midroll&amp;pod=20&amp;mridx=19&amp;rmridx=7&amp;pmnd=0&amp;pmxd=60000&amp;pmad=2&amp;vrid=1118784&amp;rdid=2d43e6e5-f1ec-47a8-81b1-10ca1ad1abe1&amp;is_amp=0&amp;dt=1599121523307&amp;idt=416&amp;dlt=1599121522102&amp;correlator=1950702064322958&amp;scor=1681105612848119&amp;sdk_apis=7,8&amp;omid_p=Google1/android.3.11.3&amp;osd=2&amp;vis=1&amp;npa=false&amp;hl=en&amp;frm=0&amp;video_doc_id=d39914eee9c3d50e21b81e01e8307eaf&amp;cmsid=2481704&amp;sdkv=h.3.237.0/n.android.3.11.3/com.mxtech.videoplayer.ad&amp;sdki=405&amp;mpt=google/exo.ext.ima&amp;mpv=2.11.3&amp;sdr=1&amp;eid=44725356&amp;an=com.mxtech.videoplayer.ad&amp;js=ima-android.3.11.3&amp;msid=com.mxtech.videoplayer.ad&amp;u_so=l&amp;is_lat=false&amp;idtype=adid&amp;mv=82161310.com.android.vending&amp;kfa=0&amp;tfcd=0]]>
      </vmap:AdTagURI>
    </vmap:AdSource>
  </vmap:AdBreak>
  <vmap:AdBreak timeOffset="00:40:00.000" breakType="linear" breakId="midroll-20">
    <vmap:AdSource id="midroll-20-ads" allowMultipleAds="true" followRedirects="true">
      <vmap:AdTagURI templateType="vast3">
        <![CDATA[https://pubads.g.doubleclick.net/gampad/ads?slotname=/21723553151/Test/Test_MXPlayer_Video1&amp;sz=400x300%7C640x480&amp;ciu_szs=1440x240&amp;cust_params=sg%3D30b,3g2,3g4,jaz,jbc,2v6,2vh,2vk,2x6,2vt,2vy,5lz,2wl,2wp,5o2,5o8,3iv,jwp,5oa,lkh,5oc,5oe,5of,5og,5op,gau,nr2,iwk,jyq,i5v,o1n,nqv,nqx,o1v,nqy,o1z,ixn,o2a,8gr,ixv,8gv,8gw,3nn,3nq,o3b,7gl,7gm,8it,8k8,8ix,8iy,8l4,8js,mss,jo3,jo8,8ke,8kf,jo9,jnm,jog,3si,cu3,k1m,352,k1w,k2h,8r7,i10,jtl,l85,hr2,80q,80s,80t,l7m,hqv,atp,5mt,oa3,k88,k87,ll7,5od,k8b,k8a,k8d,5q5,k8e,k8j,k8l,k8m,k8r,k8q,i63,o24,o25,o28,o29,k9i,k9h,k9k,iwl,k9l,k9o,k9n,lmf,lme,k9t,k9w,k9v,o1s,o1u,o1t,o1w,o1y,o1x,ocj,o40,3nf,7h6,o50,o57,o3t,hhg,ofb,ka1,ka0,ogx,69m,33k,33p,3g1,3g5,34o,34s,poa,3h8,poc,pog,3gc,cx5,3hb,cwb,3hi,5n4,3j3,3hq,3hw,cy9,cwv,cxa,cz8,3iw,oa4,6a1,cye,3l0,3l2,czd,3ku,6c0,i66,i5w,3me,ai8,3o1,3mu,nap,7g0,7g5,naz,j8v,3ni,h5x,h80,h82,hyg,nf1,oh1,nf2,msm,msl,mso,ikm,g5x,ogq,5eo,ogy,7k5,7k6,7k8,nfb,nff,jny,6hp,6hs,nge,ngi,k18%26vrsn%3DGP_1.27.1.0.charles.0.debug&amp;url=https://www.mxplayer.in/detail/episode/d39914eee9c3d50e21b81e01e8307eaf&amp;unviewed_position_start=1&amp;output=xml_vast3&amp;impl=s&amp;env=vp&amp;gdfp_req=1&amp;ad_rule=0&amp;video_url_to_fetch=https://www.mxplayer.in/detail/episode/d39914eee9c3d50e21b81e01e8307eaf&amp;cue=2400000&amp;vad_type=linear&amp;vpos=midroll&amp;pod=21&amp;mridx=20&amp;rmridx=6&amp;pmnd=0&amp;pmxd=60000&amp;pmad=2&amp;vrid=1118784&amp;rdid=2d43e6e5-f1ec-47a8-81b1-10ca1ad1abe1&amp;is_amp=0&amp;dt=1599121523307&amp;idt=416&amp;dlt=1599121522102&amp;correlator=1950702064322958&amp;scor=1681105612848119&amp;sdk_apis=7,8&amp;omid_p=Google1/android.3.11.3&amp;osd=2&amp;vis=1&amp;npa=false&amp;hl=en&amp;frm=0&amp;video_doc_id=d39914eee9c3d50e21b81e01e8307eaf&amp;cmsid=2481704&amp;sdkv=h.3.237.0/n.android.3.11.3/com.mxtech.videoplayer.ad&amp;sdki=405&amp;mpt=google/exo.ext.ima&amp;mpv=2.11.3&amp;sdr=1&amp;eid=44725356&amp;an=com.mxtech.videoplayer.ad&amp;js=ima-android.3.11.3&amp;msid=com.mxtech.videoplayer.ad&amp;u_so=l&amp;is_lat=false&amp;idtype=adid&amp;mv=82161310.com.android.vending&amp;kfa=0&amp;tfcd=0]]>
      </vmap:AdTagURI>
    </vmap:AdSource>
  </vmap:AdBreak>
  <vmap:AdBreak timeOffset="00:42:00.000" breakType="linear" breakId="midroll-21">
    <vmap:AdSource id="midroll-21-ads" allowMultipleAds="true" followRedirects="true">
      <vmap:AdTagURI templateType="vast3">
        <![CDATA[https://pubads.g.doubleclick.net/gampad/ads?slotname=/21723553151/Test/Test_MXPlayer_Video1&amp;sz=400x300%7C640x480&amp;ciu_szs=1440x240&amp;cust_params=sg%3D30b,3g2,3g4,jaz,jbc,2v6,2vh,2vk,2x6,2vt,2vy,5lz,2wl,2wp,5o2,5o8,3iv,jwp,5oa,lkh,5oc,5oe,5of,5og,5op,gau,nr2,iwk,jyq,i5v,o1n,nqv,nqx,o1v,nqy,o1z,ixn,o2a,8gr,ixv,8gv,8gw,3nn,3nq,o3b,7gl,7gm,8it,8k8,8ix,8iy,8l4,8js,mss,jo3,jo8,8ke,8kf,jo9,jnm,jog,3si,cu3,k1m,352,k1w,k2h,8r7,i10,jtl,l85,hr2,80q,80s,80t,l7m,hqv,atp,5mt,oa3,k88,k87,ll7,5od,k8b,k8a,k8d,5q5,k8e,k8j,k8l,k8m,k8r,k8q,i63,o24,o25,o28,o29,k9i,k9h,k9k,iwl,k9l,k9o,k9n,lmf,lme,k9t,k9w,k9v,o1s,o1u,o1t,o1w,o1y,o1x,ocj,o40,3nf,7h6,o50,o57,o3t,hhg,ofb,ka1,ka0,ogx,69m,33k,33p,3g1,3g5,34o,34s,poa,3h8,poc,pog,3gc,cx5,3hb,cwb,3hi,5n4,3j3,3hq,3hw,cy9,cwv,cxa,cz8,3iw,oa4,6a1,cye,3l0,3l2,czd,3ku,6c0,i66,i5w,3me,ai8,3o1,3mu,nap,7g0,7g5,naz,j8v,3ni,h5x,h80,h82,hyg,nf1,oh1,nf2,msm,msl,mso,ikm,g5x,ogq,5eo,ogy,7k5,7k6,7k8,nfb,nff,jny,6hp,6hs,nge,ngi,k18%26vrsn%3DGP_1.27.1.0.charles.0.debug&amp;url=https://www.mxplayer.in/detail/episode/d39914eee9c3d50e21b81e01e8307eaf&amp;unviewed_position_start=1&amp;output=xml_vast3&amp;impl=s&amp;env=vp&amp;gdfp_req=1&amp;ad_rule=0&amp;video_url_to_fetch=https://www.mxplayer.in/detail/episode/d39914eee9c3d50e21b81e01e8307eaf&amp;cue=2520000&amp;vad_type=linear&amp;vpos=midroll&amp;pod=22&amp;mridx=21&amp;rmridx=5&amp;pmnd=0&amp;pmxd=60000&amp;pmad=2&amp;vrid=1118784&amp;rdid=2d43e6e5-f1ec-47a8-81b1-10ca1ad1abe1&amp;is_amp=0&amp;dt=1599121523307&amp;idt=416&amp;dlt=1599121522102&amp;correlator=1950702064322958&amp;scor=1681105612848119&amp;sdk_apis=7,8&amp;omid_p=Google1/android.3.11.3&amp;osd=2&amp;vis=1&amp;npa=false&amp;hl=en&amp;frm=0&amp;video_doc_id=d39914eee9c3d50e21b81e01e8307eaf&amp;cmsid=2481704&amp;sdkv=h.3.237.0/n.android.3.11.3/com.mxtech.videoplayer.ad&amp;sdki=405&amp;mpt=google/exo.ext.ima&amp;mpv=2.11.3&amp;sdr=1&amp;eid=44725356&amp;an=com.mxtech.videoplayer.ad&amp;js=ima-android.3.11.3&amp;msid=com.mxtech.videoplayer.ad&amp;u_so=l&amp;is_lat=false&amp;idtype=adid&amp;mv=82161310.com.android.vending&amp;kfa=0&amp;tfcd=0]]>
      </vmap:AdTagURI>
    </vmap:AdSource>
  </vmap:AdBreak>
  <vmap:AdBreak timeOffset="00:44:00.000" breakType="linear" breakId="midroll-22">
    <vmap:AdSource id="midroll-22-ads" allowMultipleAds="true" followRedirects="true">
      <vmap:AdTagURI templateType="vast3">
        <![CDATA[https://pubads.g.doubleclick.net/gampad/ads?slotname=/21723553151/Test/Test_MXPlayer_Video1&amp;sz=400x300%7C640x480&amp;ciu_szs=1440x240&amp;cust_params=sg%3D30b,3g2,3g4,jaz,jbc,2v6,2vh,2vk,2x6,2vt,2vy,5lz,2wl,2wp,5o2,5o8,3iv,jwp,5oa,lkh,5oc,5oe,5of,5og,5op,gau,nr2,iwk,jyq,i5v,o1n,nqv,nqx,o1v,nqy,o1z,ixn,o2a,8gr,ixv,8gv,8gw,3nn,3nq,o3b,7gl,7gm,8it,8k8,8ix,8iy,8l4,8js,mss,jo3,jo8,8ke,8kf,jo9,jnm,jog,3si,cu3,k1m,352,k1w,k2h,8r7,i10,jtl,l85,hr2,80q,80s,80t,l7m,hqv,atp,5mt,oa3,k88,k87,ll7,5od,k8b,k8a,k8d,5q5,k8e,k8j,k8l,k8m,k8r,k8q,i63,o24,o25,o28,o29,k9i,k9h,k9k,iwl,k9l,k9o,k9n,lmf,lme,k9t,k9w,k9v,o1s,o1u,o1t,o1w,o1y,o1x,ocj,o40,3nf,7h6,o50,o57,o3t,hhg,ofb,ka1,ka0,ogx,69m,33k,33p,3g1,3g5,34o,34s,poa,3h8,poc,pog,3gc,cx5,3hb,cwb,3hi,5n4,3j3,3hq,3hw,cy9,cwv,cxa,cz8,3iw,oa4,6a1,cye,3l0,3l2,czd,3ku,6c0,i66,i5w,3me,ai8,3o1,3mu,nap,7g0,7g5,naz,j8v,3ni,h5x,h80,h82,hyg,nf1,oh1,nf2,msm,msl,mso,ikm,g5x,ogq,5eo,ogy,7k5,7k6,7k8,nfb,nff,jny,6hp,6hs,nge,ngi,k18%26vrsn%3DGP_1.27.1.0.charles.0.debug&amp;url=https://www.mxplayer.in/detail/episode/d39914eee9c3d50e21b81e01e8307eaf&amp;unviewed_position_start=1&amp;output=xml_vast3&amp;impl=s&amp;env=vp&amp;gdfp_req=1&amp;ad_rule=0&amp;video_url_to_fetch=https://www.mxplayer.in/detail/episode/d39914eee9c3d50e21b81e01e8307eaf&amp;cue=2640000&amp;vad_type=linear&amp;vpos=midroll&amp;pod=23&amp;mridx=22&amp;rmridx=4&amp;pmnd=0&amp;pmxd=60000&amp;pmad=2&amp;vrid=1118784&amp;rdid=2d43e6e5-f1ec-47a8-81b1-10ca1ad1abe1&amp;is_amp=0&amp;dt=1599121523307&amp;idt=416&amp;dlt=1599121522102&amp;correlator=1950702064322958&amp;scor=1681105612848119&amp;sdk_apis=7,8&amp;omid_p=Google1/android.3.11.3&amp;osd=2&amp;vis=1&amp;npa=false&amp;hl=en&amp;frm=0&amp;video_doc_id=d39914eee9c3d50e21b81e01e8307eaf&amp;cmsid=2481704&amp;sdkv=h.3.237.0/n.android.3.11.3/com.mxtech.videoplayer.ad&amp;sdki=405&amp;mpt=google/exo.ext.ima&amp;mpv=2.11.3&amp;sdr=1&amp;eid=44725356&amp;an=com.mxtech.videoplayer.ad&amp;js=ima-android.3.11.3&amp;msid=com.mxtech.videoplayer.ad&amp;u_so=l&amp;is_lat=false&amp;idtype=adid&amp;mv=82161310.com.android.vending&amp;kfa=0&amp;tfcd=0]]>
      </vmap:AdTagURI>
    </vmap:AdSource>
  </vmap:AdBreak>
  <vmap:AdBreak timeOffset="00:46:00.000" breakType="linear" breakId="midroll-23">
    <vmap:AdSource id="midroll-23-ads" allowMultipleAds="true" followRedirects="true">
      <vmap:AdTagURI templateType="vast3">
        <![CDATA[https://pubads.g.doubleclick.net/gampad/ads?slotname=/21723553151/Test/Test_MXPlayer_Video1&amp;sz=400x300%7C640x480&amp;ciu_szs=1440x240&amp;cust_params=sg%3D30b,3g2,3g4,jaz,jbc,2v6,2vh,2vk,2x6,2vt,2vy,5lz,2wl,2wp,5o2,5o8,3iv,jwp,5oa,lkh,5oc,5oe,5of,5og,5op,gau,nr2,iwk,jyq,i5v,o1n,nqv,nqx,o1v,nqy,o1z,ixn,o2a,8gr,ixv,8gv,8gw,3nn,3nq,o3b,7gl,7gm,8it,8k8,8ix,8iy,8l4,8js,mss,jo3,jo8,8ke,8kf,jo9,jnm,jog,3si,cu3,k1m,352,k1w,k2h,8r7,i10,jtl,l85,hr2,80q,80s,80t,l7m,hqv,atp,5mt,oa3,k88,k87,ll7,5od,k8b,k8a,k8d,5q5,k8e,k8j,k8l,k8m,k8r,k8q,i63,o24,o25,o28,o29,k9i,k9h,k9k,iwl,k9l,k9o,k9n,lmf,lme,k9t,k9w,k9v,o1s,o1u,o1t,o1w,o1y,o1x,ocj,o40,3nf,7h6,o50,o57,o3t,hhg,ofb,ka1,ka0,ogx,69m,33k,33p,3g1,3g5,34o,34s,poa,3h8,poc,pog,3gc,cx5,3hb,cwb,3hi,5n4,3j3,3hq,3hw,cy9,cwv,cxa,cz8,3iw,oa4,6a1,cye,3l0,3l2,czd,3ku,6c0,i66,i5w,3me,ai8,3o1,3mu,nap,7g0,7g5,naz,j8v,3ni,h5x,h80,h82,hyg,nf1,oh1,nf2,msm,msl,mso,ikm,g5x,ogq,5eo,ogy,7k5,7k6,7k8,nfb,nff,jny,6hp,6hs,nge,ngi,k18%26vrsn%3DGP_1.27.1.0.charles.0.debug&amp;url=https://www.mxplayer.in/detail/episode/d39914eee9c3d50e21b81e01e8307eaf&amp;unviewed_position_start=1&amp;output=xml_vast3&amp;impl=s&amp;env=vp&amp;gdfp_req=1&amp;ad_rule=0&amp;video_url_to_fetch=https://www.mxplayer.in/detail/episode/d39914eee9c3d50e21b81e01e8307eaf&amp;cue=2760000&amp;vad_type=linear&amp;vpos=midroll&amp;pod=24&amp;mridx=23&amp;rmridx=3&amp;pmnd=0&amp;pmxd=60000&amp;pmad=2&amp;vrid=1118784&amp;rdid=2d43e6e5-f1ec-47a8-81b1-10ca1ad1abe1&amp;is_amp=0&amp;dt=1599121523307&amp;idt=416&amp;dlt=1599121522102&amp;correlator=1950702064322958&amp;scor=1681105612848119&amp;sdk_apis=7,8&amp;omid_p=Google1/android.3.11.3&amp;osd=2&amp;vis=1&amp;npa=false&amp;hl=en&amp;frm=0&amp;video_doc_id=d39914eee9c3d50e21b81e01e8307eaf&amp;cmsid=2481704&amp;sdkv=h.3.237.0/n.android.3.11.3/com.mxtech.videoplayer.ad&amp;sdki=405&amp;mpt=google/exo.ext.ima&amp;mpv=2.11.3&amp;sdr=1&amp;eid=44725356&amp;an=com.mxtech.videoplayer.ad&amp;js=ima-android.3.11.3&amp;msid=com.mxtech.videoplayer.ad&amp;u_so=l&amp;is_lat=false&amp;idtype=adid&amp;mv=82161310.com.android.vending&amp;kfa=0&amp;tfcd=0]]>
      </vmap:AdTagURI>
    </vmap:AdSource>
  </vmap:AdBreak>
  <vmap:AdBreak timeOffset="00:48:00.000" breakType="linear" breakId="midroll-24">
    <vmap:AdSource id="midroll-24-ads" allowMultipleAds="true" followRedirects="true">
      <vmap:AdTagURI templateType="vast3">
        <![CDATA[https://pubads.g.doubleclick.net/gampad/ads?slotname=/21723553151/Test/Test_MXPlayer_Video1&amp;sz=400x300%7C640x480&amp;ciu_szs=1440x240&amp;cust_params=sg%3D30b,3g2,3g4,jaz,jbc,2v6,2vh,2vk,2x6,2vt,2vy,5lz,2wl,2wp,5o2,5o8,3iv,jwp,5oa,lkh,5oc,5oe,5of,5og,5op,gau,nr2,iwk,jyq,i5v,o1n,nqv,nqx,o1v,nqy,o1z,ixn,o2a,8gr,ixv,8gv,8gw,3nn,3nq,o3b,7gl,7gm,8it,8k8,8ix,8iy,8l4,8js,mss,jo3,jo8,8ke,8kf,jo9,jnm,jog,3si,cu3,k1m,352,k1w,k2h,8r7,i10,jtl,l85,hr2,80q,80s,80t,l7m,hqv,atp,5mt,oa3,k88,k87,ll7,5od,k8b,k8a,k8d,5q5,k8e,k8j,k8l,k8m,k8r,k8q,i63,o24,o25,o28,o29,k9i,k9h,k9k,iwl,k9l,k9o,k9n,lmf,lme,k9t,k9w,k9v,o1s,o1u,o1t,o1w,o1y,o1x,ocj,o40,3nf,7h6,o50,o57,o3t,hhg,ofb,ka1,ka0,ogx,69m,33k,33p,3g1,3g5,34o,34s,poa,3h8,poc,pog,3gc,cx5,3hb,cwb,3hi,5n4,3j3,3hq,3hw,cy9,cwv,cxa,cz8,3iw,oa4,6a1,cye,3l0,3l2,czd,3ku,6c0,i66,i5w,3me,ai8,3o1,3mu,nap,7g0,7g5,naz,j8v,3ni,h5x,h80,h82,hyg,nf1,oh1,nf2,msm,msl,mso,ikm,g5x,ogq,5eo,ogy,7k5,7k6,7k8,nfb,nff,jny,6hp,6hs,nge,ngi,k18%26vrsn%3DGP_1.27.1.0.charles.0.debug&amp;url=https://www.mxplayer.in/detail/episode/d39914eee9c3d50e21b81e01e8307eaf&amp;unviewed_position_start=1&amp;output=xml_vast3&amp;impl=s&amp;env=vp&amp;gdfp_req=1&amp;ad_rule=0&amp;video_url_to_fetch=https://www.mxplayer.in/detail/episode/d39914eee9c3d50e21b81e01e8307eaf&amp;cue=2880000&amp;vad_type=linear&amp;vpos=midroll&amp;pod=25&amp;mridx=24&amp;rmridx=2&amp;pmnd=0&amp;pmxd=60000&amp;pmad=2&amp;vrid=1118784&amp;rdid=2d43e6e5-f1ec-47a8-81b1-10ca1ad1abe1&amp;is_amp=0&amp;dt=1599121523307&amp;idt=416&amp;dlt=1599121522102&amp;correlator=1950702064322958&amp;scor=1681105612848119&amp;sdk_apis=7,8&amp;omid_p=Google1/android.3.11.3&amp;osd=2&amp;vis=1&amp;npa=false&amp;hl=en&amp;frm=0&amp;video_doc_id=d39914eee9c3d50e21b81e01e8307eaf&amp;cmsid=2481704&amp;sdkv=h.3.237.0/n.android.3.11.3/com.mxtech.videoplayer.ad&amp;sdki=405&amp;mpt=google/exo.ext.ima&amp;mpv=2.11.3&amp;sdr=1&amp;eid=44725356&amp;an=com.mxtech.videoplayer.ad&amp;js=ima-android.3.11.3&amp;msid=com.mxtech.videoplayer.ad&amp;u_so=l&amp;is_lat=false&amp;idtype=adid&amp;mv=82161310.com.android.vending&amp;kfa=0&amp;tfcd=0]]>
      </vmap:AdTagURI>
    </vmap:AdSource>
  </vmap:AdBreak>
  <vmap:AdBreak timeOffset="00:50:00.000" breakType="linear" breakId="midroll-25">
    <vmap:AdSource id="midroll-25-ads" allowMultipleAds="true" followRedirects="true">
      <vmap:AdTagURI templateType="vast3">
        <![CDATA[https://pubads.g.doubleclick.net/gampad/ads?slotname=/21723553151/Test/Test_MXPlayer_Video1&amp;sz=400x300%7C640x480&amp;ciu_szs=1440x240&amp;cust_params=sg%3D30b,3g2,3g4,jaz,jbc,2v6,2vh,2vk,2x6,2vt,2vy,5lz,2wl,2wp,5o2,5o8,3iv,jwp,5oa,lkh,5oc,5oe,5of,5og,5op,gau,nr2,iwk,jyq,i5v,o1n,nqv,nqx,o1v,nqy,o1z,ixn,o2a,8gr,ixv,8gv,8gw,3nn,3nq,o3b,7gl,7gm,8it,8k8,8ix,8iy,8l4,8js,mss,jo3,jo8,8ke,8kf,jo9,jnm,jog,3si,cu3,k1m,352,k1w,k2h,8r7,i10,jtl,l85,hr2,80q,80s,80t,l7m,hqv,atp,5mt,oa3,k88,k87,ll7,5od,k8b,k8a,k8d,5q5,k8e,k8j,k8l,k8m,k8r,k8q,i63,o24,o25,o28,o29,k9i,k9h,k9k,iwl,k9l,k9o,k9n,lmf,lme,k9t,k9w,k9v,o1s,o1u,o1t,o1w,o1y,o1x,ocj,o40,3nf,7h6,o50,o57,o3t,hhg,ofb,ka1,ka0,ogx,69m,33k,33p,3g1,3g5,34o,34s,poa,3h8,poc,pog,3gc,cx5,3hb,cwb,3hi,5n4,3j3,3hq,3hw,cy9,cwv,cxa,cz8,3iw,oa4,6a1,cye,3l0,3l2,czd,3ku,6c0,i66,i5w,3me,ai8,3o1,3mu,nap,7g0,7g5,naz,j8v,3ni,h5x,h80,h82,hyg,nf1,oh1,nf2,msm,msl,mso,ikm,g5x,ogq,5eo,ogy,7k5,7k6,7k8,nfb,nff,jny,6hp,6hs,nge,ngi,k18%26vrsn%3DGP_1.27.1.0.charles.0.debug&amp;url=https://www.mxplayer.in/detail/episode/d39914eee9c3d50e21b81e01e8307eaf&amp;unviewed_position_start=1&amp;output=xml_vast3&amp;impl=s&amp;env=vp&amp;gdfp_req=1&amp;ad_rule=0&amp;video_url_to_fetch=https://www.mxplayer.in/detail/episode/d39914eee9c3d50e21b81e01e8307eaf&amp;cue=3000000&amp;vad_type=linear&amp;vpos=midroll&amp;pod=26&amp;mridx=25&amp;rmridx=1&amp;pmnd=0&amp;pmxd=60000&amp;pmad=2&amp;vrid=1118784&amp;rdid=2d43e6e5-f1ec-47a8-81b1-10ca1ad1abe1&amp;is_amp=0&amp;dt=1599121523307&amp;idt=416&amp;dlt=1599121522102&amp;correlator=1950702064322958&amp;scor=1681105612848119&amp;sdk_apis=7,8&amp;omid_p=Google1/android.3.11.3&amp;osd=2&amp;vis=1&amp;npa=false&amp;hl=en&amp;frm=0&amp;video_doc_id=d39914eee9c3d50e21b81e01e8307eaf&amp;cmsid=2481704&amp;sdkv=h.3.237.0/n.android.3.11.3/com.mxtech.videoplayer.ad&amp;sdki=405&amp;mpt=google/exo.ext.ima&amp;mpv=2.11.3&amp;sdr=1&amp;eid=44725356&amp;an=com.mxtech.videoplayer.ad&amp;js=ima-android.3.11.3&amp;msid=com.mxtech.videoplayer.ad&amp;u_so=l&amp;is_lat=false&amp;idtype=adid&amp;mv=82161310.com.android.vending&amp;kfa=0&amp;tfcd=0]]>
      </vmap:AdTagURI>
    </vmap:AdSource>
  </vmap:AdBreak>
</vmap:VMAP>